{"error":false,"code":null,"voters":[{"o":11024558,"f":"נאהד","l":"אבו חמאד","v":"066601188","p":"","a":"דריג'את 0, דריג'את","s":0,"t":0,"vo":false,"ci":359},{"o":13769941,"f":"זקי","l":"אבן חמאד","v":"026211490","p":"","a":"דריג'את 0, דריג'את","s":0,"t":0,"vo":false,"ci":359},{"o":9730204,"f":"חאדר","l":"אבו חמאד","v":"318857562","p":"","a":"דריג'את 0, דריג'את","s":0,"t":0,"vo":false,"ci":359},{"o":8147061,"f":"בדעה","l":"אבו רביעה","v":"300566015","p":"","a":"דריג'את 0, דריג'את","s":0,"t":0,"vo":false,"ci":359},{"o":10275984,"f":"נאסר","l":"אבו רביעה","v":"203670245","p":"","a":"דריג'את 0, דריג'את","s":0,"t":0,"vo":false,"ci":359},{"o":9959577,"f":"עומר","l":"אבו רביעה","v":"056872823","p":"","a":"דריג'את 0, דריג'את","s":0,"t":0,"vo":false,"ci":359},{"o":9397404,"f":"נעמה","l":"אבו גריבה","v":"066459108","p":"","a":"דריג'את 0, דריג'את","s":0,"t":0,"vo":false,"ci":359},{"o":10088591,"f":"מוחמד","l":"אבו כרש","v":"209471150","p":"","a":"דריג'את 0, דריג'את","s":0,"t":0,"vo":false,"ci":359},{"o":11816109,"f":"נידאה","l":"עמרו","v":"032502130","p":"","a":"דריג'את 0, דריג'את","s":0,"t":0,"vo":false,"ci":359},{"o":8309858,"f":"סארה","l":"אבו חמאד","v":"315931063","p":"","a":"דריג'את 0, דריג'את","s":0,"t":0,"vo":false,"ci":359},{"o":11868329,"f":"סאמח","l":"אבו חמאד","v":"318885845","p":"","a":"דריג'את 0, דריג'את","s":0,"t":0,"vo":false,"ci":359},{"o":7766120,"f":"לילה","l":"אבו חמאד","v":"036462802","p":"","a":"דריג'את 0, דריג'את","s":0,"t":0,"vo":false,"ci":359},{"o":8199267,"f":"מרפת","l":"אבו חמאד","v":"300135845","p":"","a":"דריג'את 0, דריג'את","s":0,"t":0,"vo":false,"ci":359},{"o":10584255,"f":"חמאד","l":"אבו חמאד","v":"208892695","p":"","a":"דריג'את 0, דריג'את","s":0,"t":0,"vo":false,"ci":359},{"o":8215645,"f":"עבד אללה","l":"חאג' עאמר","v":"312192529","p":"","a":"דריג'את 0, דריג'את","s":0,"t":0,"vo":false,"ci":359},{"o":13338859,"f":"אדם","l":"אבו רביעה","v":"026421560","p":"","a":"דריג'את 0, דריג'את","s":0,"t":0,"vo":false,"ci":359},{"o":12636385,"f":"חלימה","l":"אבו רביעה","v":"313186652","p":"","a":"דריג'את 0, דריג'את","s":0,"t":0,"vo":false,"ci":359},{"o":13608174,"f":"אנואר","l":"אבו חאמד","v":"206749830","p":"","a":"דריג'את 0, דריג'את","s":0,"t":0,"vo":false,"ci":359},{"o":13152492,"f":"עניאן","l":"אבו רביעה","v":"313254773","p":"","a":"דריג'את 0, דריג'את","s":0,"t":0,"vo":false,"ci":359},{"o":12952803,"f":"ג'ואד","l":"אבו רביעה","v":"304805799","p":"","a":"דריג'את 0, דריג'את","s":0,"t":0,"vo":false,"ci":359},{"o":13388006,"f":"טאלב","l":"אבו חמאד","v":"059519900","p":"","a":"דריג'את 0, דריג'את","s":0,"t":0,"vo":false,"ci":359},{"o":13143267,"f":"נואל","l":"אלחואמדה","v":"037244845","p":"","a":"דריג'את 0, דריג'את","s":0,"t":0,"vo":false,"ci":359},{"o":13490406,"f":"גהאד","l":"אבו חמאד","v":"026427989","p":"","a":"דריג'את 0, דריג'את","s":0,"t":0,"vo":false,"ci":359},{"o":9432224,"f":"דהב","l":"אבו חמאד","v":"035188796","p":"","a":"דריג'את 0, דריג'את","s":0,"t":0,"vo":false,"ci":359},{"o":12606705,"f":"אבראהים","l":"חאג' עאמר","v":"311429047","p":"","a":"דריג'את 0, דריג'את","s":0,"t":0,"vo":false,"ci":359},{"o":10803344,"f":"סוזאן","l":"אבו חמאד","v":"208032011","p":"","a":"דריג'את 0, דריג'את","s":0,"t":0,"vo":false,"ci":359},{"o":11476122,"f":"רסמיה","l":"חאג' עאמר","v":"313384364","p":"","a":"דריג'את 0, דריג'את","s":0,"t":0,"vo":false,"ci":359},{"o":7429190,"f":"מרים","l":"חאג' חסן","v":"039633243","p":"","a":"דריג'את 0, דריג'את","s":0,"t":0,"vo":false,"ci":359},{"o":12614903,"f":"מונה","l":"דיבאן","v":"328051883","p":"","a":"דריג'את 0, דריג'את","s":0,"t":0,"vo":false,"ci":359},{"o":12904702,"f":"יוסף","l":"אבו רביעה","v":"304803794","p":"","a":"דריג'את 0, דריג'את","s":0,"t":0,"vo":false,"ci":359},{"o":14006504,"f":"ראוי","l":"אבו עינים","v":"204439194","p":"","a":"דריג'את 0, דריג'את","s":0,"t":0,"vo":false,"ci":359},{"o":11248789,"f":"אלחסן","l":"אבו חמאד אלעוודה","v":"314801952","p":"","a":"דריג'את 0, דריג'את","s":0,"t":0,"vo":false,"ci":359},{"o":8600764,"f":"טלאל","l":"אבו חמאד","v":"300577186","p":"","a":"דריג'את 0, דריג'את","s":0,"t":0,"vo":false,"ci":359},{"o":9969831,"f":"ראדי","l":"ארייט","v":"056872948","p":"","a":"דריג'את 0, דריג'את","s":0,"t":0,"vo":false,"ci":359},{"o":10088614,"f":"דיראר","l":"אבו כרש","v":"209471143","p":"","a":"דריג'את 0, דריג'את","s":0,"t":0,"vo":false,"ci":359},{"o":7644213,"f":"מרים","l":"אבו חמאד","v":"200246247","p":"","a":"דריג'את 0, דריג'את","s":0,"t":0,"vo":false,"ci":359},{"o":8411329,"f":"תמאם","l":"ארייט","v":"201330560","p":"","a":"דריג'את 0, דריג'את","s":0,"t":0,"vo":false,"ci":359},{"o":10011865,"f":"כמאל","l":"אבו רביעה","v":"311268981","p":"","a":"דריג'את 0, דריג'את","s":0,"t":0,"vo":false,"ci":359},{"o":13922463,"f":"אמינה","l":"אבו רביעה","v":"032965444","p":"","a":"דריג'את 0, דריג'את","s":0,"t":0,"vo":false,"ci":359},{"o":12536047,"f":"בטרסיה","l":"אבו חמאד אלעווד","v":"040098204","p":"","a":"דריג'את 0, דריג'את","s":0,"t":0,"vo":false,"ci":359},{"o":8702166,"f":"ענאם","l":"אבו חמאד","v":"028330132","p":"","a":"דריג'את 0, דריג'את","s":0,"t":0,"vo":false,"ci":359},{"o":9711810,"f":"הודא","l":"אבו רביעה","v":"302105226","p":"","a":"דריג'את 0, דריג'את","s":0,"t":0,"vo":false,"ci":359},{"o":13882501,"f":"אסמאעיל","l":"חאג' עאמר","v":"318542321","p":"","a":"דריג'את 0, דריג'את","s":0,"t":0,"vo":false,"ci":359},{"o":9575624,"f":"זיינב","l":"אבו רביעה","v":"052452893","p":"","a":"דריג'את 0, דריג'את","s":0,"t":0,"vo":false,"ci":359},{"o":10341575,"f":"עאליה","l":"אבו רביעה","v":"034028100","p":"","a":"דריג'את 0, דריג'את","s":0,"t":0,"vo":false,"ci":359},{"o":10860798,"f":"טארק","l":"אבו חמאד","v":"315108035","p":"","a":"דריג'את 0, דריג'את","s":0,"t":0,"vo":false,"ci":359},{"o":12569826,"f":"סוהירה","l":"שלבי","v":"030415061","p":"","a":"דריג'את 0, דריג'את","s":0,"t":0,"vo":false,"ci":359},{"o":8904921,"f":"סמר","l":"חאג' שאקר","v":"315388090","p":"","a":"דריג'את 0, דריג'את","s":0,"t":0,"vo":false,"ci":359},{"o":13959306,"f":"רפיק","l":"אבו חמאד","v":"042833723","p":"","a":"דריג'את 0, דריג'את","s":0,"t":0,"vo":false,"ci":359},{"o":13890739,"f":"נגמה","l":"אבו חמאד","v":"058161415","p":"","a":"דריג'את 0, דריג'את","s":0,"t":0,"vo":false,"ci":359},{"o":13885618,"f":"פארס","l":"אבו רביעה","v":"300060894","p":"","a":"דריג'את 0, דריג'את","s":0,"t":0,"vo":false,"ci":359},{"o":10212605,"f":"מחמד","l":"חאג' עאמר","v":"023352081","p":"","a":"דריג'את 0, דריג'את","s":0,"t":0,"vo":false,"ci":359},{"o":9329894,"f":"מרים","l":"אבו חמאד","v":"029854304","p":"","a":"דריג'את 0, דריג'את","s":0,"t":0,"vo":false,"ci":359},{"o":8420585,"f":"מאג'דה","l":"אבו חמאד","v":"032487639","p":"","a":"דריג'את 0, דריג'את","s":0,"t":0,"vo":false,"ci":359},{"o":8718572,"f":"אחמד","l":"אבו רביעה","v":"040108045","p":"","a":"דריג'את 0, דריג'את","s":0,"t":0,"vo":false,"ci":359},{"o":12805289,"f":"אמיר","l":"אבו חמאד","v":"318745312","p":"","a":"דריג'את 0, דריג'את","s":0,"t":0,"vo":false,"ci":359},{"o":10030322,"f":"עביר","l":"אבו חמאד","v":"200272524","p":"","a":"דריג'את 0, דריג'את","s":0,"t":0,"vo":false,"ci":359},{"o":12117203,"f":"אדיב","l":"אבו חמאד","v":"026342378","p":"","a":"דריג'את 0, דריג'את","s":0,"t":0,"vo":false,"ci":359},{"o":13375655,"f":"אמינה","l":"אבו חמאד","v":"311373500","p":"","a":"דריג'את 0, דריג'את","s":0,"t":0,"vo":false,"ci":359},{"o":12538065,"f":"ריאדי","l":"אבו חמאד","v":"037172285","p":"","a":"דריג'את 0, דריג'את","s":0,"t":0,"vo":false,"ci":359},{"o":8661227,"f":"מורד","l":"אבו חמאד","v":"200258176","p":"","a":"דריג'את 0, דריג'את","s":0,"t":0,"vo":false,"ci":359},{"o":9982184,"f":"אחלאם","l":"אבו חמאד","v":"209259902","p":"","a":"דריג'את 0, דריג'את","s":0,"t":0,"vo":false,"ci":359},{"o":8517872,"f":"כאפה","l":"אבו חמאד","v":"037768785","p":"","a":"דריג'את 0, דריג'את","s":0,"t":0,"vo":false,"ci":359},{"o":9461989,"f":"אניסה","l":"אבו חמאד","v":"207369372","p":"","a":"דריג'את 0, דריג'את","s":0,"t":0,"vo":false,"ci":359},{"o":9800930,"f":"שאימה","l":"מסארוה","v":"301393997","p":"","a":"דריג'את 0, דריג'את","s":0,"t":0,"vo":false,"ci":359},{"o":10864850,"f":"ראתב","l":"אבו חמאד","v":"033015678","p":"","a":"דריג'את 0, דריג'את","s":0,"t":0,"vo":false,"ci":359},{"o":8885500,"f":"נור","l":"אבו חמאד","v":"211856216","p":"","a":"דריג'את 0, דריג'את","s":0,"t":0,"vo":false,"ci":359},{"o":8239357,"f":"מחמד","l":"חאג' עאמר","v":"312194467","p":"","a":"דריג'את 0, דריג'את","s":0,"t":0,"vo":false,"ci":359},{"o":8756229,"f":"נאסים","l":"אבו-חמאד אלעוודה","v":"208374116","p":"","a":"דריג'את 0, דריג'את","s":0,"t":0,"vo":false,"ci":359},{"o":12147769,"f":"חסן","l":"אבו חמאד","v":"023162183","p":"","a":"דריג'את 0, דריג'את","s":0,"t":0,"vo":false,"ci":359},{"o":13953109,"f":"מייסון","l":"אבו רביעה","v":"318544319","p":"","a":"דריג'את 0, דריג'את","s":0,"t":0,"vo":false,"ci":359},{"o":12342334,"f":"מוחמד","l":"אבן חמאד","v":"211966890","p":"","a":"דריג'את 0, דריג'את","s":0,"t":0,"vo":false,"ci":359},{"o":8777734,"f":"רשא","l":"אבו חמאד","v":"209391952","p":"","a":"דריג'את 0, דריג'את","s":0,"t":0,"vo":false,"ci":359},{"o":9434123,"f":"עאישה","l":"אבו רביעה","v":"035188630","p":"","a":"דריג'את 143, דריג'את","s":0,"t":0,"vo":false,"ci":359},{"o":11416618,"f":"ראוון","l":"אבו חמאד","v":"211305354","p":"","a":"דריג'את 0, דריג'את","s":0,"t":0,"vo":false,"ci":359},{"o":14002271,"f":"חרבה","l":"סאנע","v":"035001411","p":"","a":"דריג'את 0, דריג'את","s":0,"t":0,"vo":false,"ci":359},{"o":11403301,"f":"מחמד","l":"אבו רביעה","v":"066114208","p":"","a":"דריג'את 0, דריג'את","s":0,"t":0,"vo":false,"ci":359},{"o":11514916,"f":"סומיה","l":"אבו רביעה","v":"312211360","p":"","a":"דריג'את 0, דריג'את","s":0,"t":0,"vo":false,"ci":359},{"o":8428558,"f":"חסין","l":"אבו חמאד","v":"301718722","p":"","a":"דריג'את 0, דריג'את","s":0,"t":0,"vo":false,"ci":359},{"o":12212277,"f":"מאנל","l":"אבו חמאד","v":"040152266","p":"","a":"דריג'את 0, דריג'את","s":0,"t":0,"vo":false,"ci":359},{"o":13588575,"f":"כאמלה","l":"אבו חמאד","v":"053717823","p":"","a":"דריג'את 0, דריג'את","s":0,"t":0,"vo":false,"ci":359},{"o":11047993,"f":"אמאל","l":"אבו חמאד","v":"066602830","p":"","a":"דריג'את 0, דריג'את","s":0,"t":0,"vo":false,"ci":359},{"o":13041746,"f":"מחמד","l":"חאג' עאמר","v":"304809460","p":"","a":"דריג'את 0, דריג'את","s":0,"t":0,"vo":false,"ci":359},{"o":9985039,"f":"זהרה","l":"אבו חמאד","v":"056871494","p":"","a":"דריג'את 0, דריג'את","s":0,"t":0,"vo":false,"ci":359},{"o":12222498,"f":"תאופיק","l":"חאג' עאמר","v":"033467119","p":"","a":"דריג'את 0, דריג'את","s":0,"t":0,"vo":false,"ci":359},{"o":13006942,"f":"יחיא","l":"אבו רביעה","v":"301904801","p":"","a":"דריג'את 0, דריג'את","s":0,"t":0,"vo":false,"ci":359},{"o":7819479,"f":"מרלין","l":"אבן חמאד","v":"317753150","p":"","a":"דריג'את 0, דריג'את","s":0,"t":0,"vo":false,"ci":359},{"o":10174523,"f":"איפטיסם","l":"אבו חאמד","v":"025880634","p":"","a":"דריג'את 0, דריג'את","s":0,"t":0,"vo":false,"ci":359},{"o":13826162,"f":"שאדיה","l":"אבו חמאד","v":"308306778","p":"","a":"דריג'את 0, דריג'את","s":0,"t":0,"vo":false,"ci":359},{"o":7765204,"f":"היתם","l":"אבו חמאד","v":"313279408","p":"","a":"דריג'את 0, דריג'את","s":0,"t":0,"vo":false,"ci":359},{"o":9650225,"f":"נור","l":"אבו רביעה","v":"206410789","p":"","a":"דריג'את 0, דריג'את","s":0,"t":0,"vo":false,"ci":359},{"o":8875044,"f":"עאדל","l":"אל מחאריק","v":"313908410","p":"","a":"דריג'את 0, דריג'את","s":0,"t":0,"vo":false,"ci":359},{"o":10550280,"f":"רטיבה","l":"אבו חמאד","v":"059413302","p":"","a":"דריג'את 0, דריג'את","s":0,"t":0,"vo":false,"ci":359},{"o":10578952,"f":"פואד","l":"אבו חמאד","v":"026479618","p":"","a":"דריג'את 0, דריג'את","s":0,"t":0,"vo":false,"ci":359},{"o":11533318,"f":"אחמד","l":"אבן חמאד","v":"319035432","p":"","a":"דריג'את 0, דריג'את","s":0,"t":0,"vo":false,"ci":359},{"o":13060214,"f":"חיתאם","l":"אבו רביעה","v":"301904975","p":"","a":"דריג'את 0, דריג'את","s":0,"t":0,"vo":false,"ci":359},{"o":9359420,"f":"ביאלל","l":"חאג' עאמר","v":"205977705","p":"","a":"דריג'את 0, דריג'את","s":0,"t":0,"vo":false,"ci":359},{"o":7831745,"f":"זהרה","l":"אבו חמאד","v":"036468130","p":"","a":"דריג'את 0, דריג'את","s":0,"t":0,"vo":false,"ci":359},{"o":7457990,"f":"חלאס","l":"אבו חמאד","v":"203295597","p":"","a":"דריג'את 0, דריג'את","s":0,"t":0,"vo":false,"ci":359},{"o":8059085,"f":"אינאס","l":"אבו חמאד","v":"204500482","p":"","a":"דריג'את 0, דריג'את","s":0,"t":0,"vo":false,"ci":359},{"o":9274420,"f":"ניירוז","l":"אבו חמאד","v":"212661839","p":"","a":"דריג'את 0, דריג'את","s":0,"t":0,"vo":false,"ci":359},{"o":13782123,"f":"כפאח","l":"חאג' עאמר","v":"304752603","p":"","a":"דריג'את 0, דריג'את","s":0,"t":0,"vo":false,"ci":359},{"o":13212787,"f":"חתם","l":"אבו חמאד","v":"302583638","p":"","a":"דריג'את 0, דריג'את","s":0,"t":0,"vo":false,"ci":359},{"o":8345795,"f":"אמיר","l":"אבו רביעה","v":"308101450","p":"","a":"דריג'את 0, דריג'את","s":0,"t":0,"vo":false,"ci":359},{"o":9122870,"f":"אחמד","l":"אבו חמאד","v":"206067522","p":"","a":"דריג'את 0, דריג'את","s":0,"t":0,"vo":false,"ci":359},{"o":9902121,"f":"אסעד","l":"אבו רביעה","v":"311264600","p":"","a":"דריג'את 0, דריג'את","s":0,"t":0,"vo":false,"ci":359},{"o":12555265,"f":"ורדי","l":"אבו רביעה","v":"318894862","p":"","a":"דריג'את 0, דריג'את","s":0,"t":0,"vo":false,"ci":359},{"o":10080345,"f":"עיסא","l":"אבו חמאד","v":"305507170","p":"","a":"דריג'את 0, דריג'את","s":0,"t":0,"vo":false,"ci":359},{"o":10290264,"f":"עמראן","l":"חאג' עאמר","v":"059905745","p":"","a":"דריג'את 0, דריג'את","s":0,"t":0,"vo":false,"ci":359},{"o":7427254,"f":"חנאן","l":"אלחואמדה","v":"031519796","p":"","a":"דריג'את 0, דריג'את","s":0,"t":0,"vo":false,"ci":359},{"o":7451833,"f":"לובנה","l":"אבו חמאד","v":"323848119","p":"","a":"דריג'את 0, דריג'את","s":0,"t":0,"vo":false,"ci":359},{"o":7741629,"f":"נג'יה","l":"אלזעאריר","v":"033280959","p":"","a":"דריג'את 0, דריג'את","s":0,"t":0,"vo":false,"ci":359},{"o":12006524,"f":"מעזוזה","l":"אבן חמאד","v":"315275750","p":"","a":"דריג'את 0, דריג'את","s":0,"t":0,"vo":false,"ci":359},{"o":13798425,"f":"ואהיב","l":"אבו חמאד","v":"308303999","p":"","a":"דריג'את 0, דריג'את","s":0,"t":0,"vo":false,"ci":359},{"o":12130423,"f":"יונס","l":"אבן חמאד","v":"035628494","p":"","a":"דריג'את 0, דריג'את","s":0,"t":0,"vo":false,"ci":359},{"o":9881689,"f":"אמיר","l":"אבו-חמאד אלעוודה","v":"209255223","p":"","a":"דריג'את 0, דריג'את","s":0,"t":0,"vo":false,"ci":359},{"o":9731140,"f":"מוחמד","l":"אבו חמאד אלעוודה","v":"206411696","p":"","a":"דריג'את 0, דריג'את","s":0,"t":0,"vo":false,"ci":359},{"o":8365229,"f":"עליה","l":"אבו רביעה","v":"301004198","p":"","a":"דריג'את 0, דריג'את","s":0,"t":0,"vo":false,"ci":359},{"o":7672998,"f":"זאהי","l":"אבו חמאד","v":"200248466","p":"","a":"דריג'את 0, דריג'את","s":0,"t":0,"vo":false,"ci":359},{"o":9667655,"f":"באקר","l":"אבו חמאד","v":"318855244","p":"","a":"דריג'את 0, דריג'את","s":0,"t":0,"vo":false,"ci":359},{"o":9959502,"f":"דיאב","l":"אבו חמאד","v":"056872898","p":"","a":"דריג'את 0, דריג'את","s":0,"t":0,"vo":false,"ci":359},{"o":9856077,"f":"זאייד","l":"אבן חמאד","v":"209256353","p":"","a":"דריג'את 0, דריג'את","s":0,"t":0,"vo":false,"ci":359},{"o":8165536,"f":"פאהמי","l":"אבו חמאד","v":"034080309","p":"","a":"דריג'את 0, דריג'את","s":0,"t":0,"vo":false,"ci":359},{"o":10233920,"f":"ודחה","l":"אבו חמאד","v":"023351083","p":"","a":"דריג'את 0, דריג'את","s":0,"t":0,"vo":false,"ci":359},{"o":12665885,"f":"אנעם","l":"אבו חמאד","v":"031434186","p":"","a":"דריג'את 0, דריג'את","s":0,"t":0,"vo":false,"ci":359},{"o":12698655,"f":"נאיל","l":"אבו חמאד","v":"026139550","p":"","a":"דריג'את 0, דריג'את","s":0,"t":0,"vo":false,"ci":359},{"o":13684751,"f":"נאדין","l":"אבו חמאד","v":"319065157","p":"","a":"דריג'את 0, דריג'את","s":0,"t":0,"vo":false,"ci":359},{"o":11663441,"f":"אנס","l":"ארייט","v":"312585771","p":"","a":"דריג'את 0, דריג'את","s":0,"t":0,"vo":false,"ci":359},{"o":10290302,"f":"ג'באר","l":"אבו חמאד","v":"059905760","p":"","a":"דריג'את 0, דריג'את","s":0,"t":0,"vo":false,"ci":359},{"o":12912673,"f":"פאיז","l":"אבו רביעה","v":"201394707","p":"","a":"דריג'את 0, דריג'את","s":0,"t":0,"vo":false,"ci":359},{"o":11170882,"f":"דיאנה","l":"אבו חמאד","v":"207239435","p":"","a":"דריג'את 0, דריג'את","s":0,"t":0,"vo":false,"ci":359},{"o":11520069,"f":"היאם","l":"אבו חמאד","v":"066119066","p":"","a":"דריג'את 0, דריג'את","s":0,"t":0,"vo":false,"ci":359},{"o":13044781,"f":"באג'ס","l":"אבו חמאד אלעוודה","v":"211609516","p":"","a":"דריג'את 0, דריג'את","s":0,"t":0,"vo":false,"ci":359},{"o":13986878,"f":"מחמד","l":"אבו חמאד","v":"037192796","p":"","a":"דריג'את 0, דריג'את","s":0,"t":0,"vo":false,"ci":359},{"o":7741595,"f":"נג'ווה","l":"אבו רביעה","v":"033280942","p":"","a":"דריג'את 0, דריג'את","s":0,"t":0,"vo":false,"ci":359},{"o":9885819,"f":"עביר","l":"אבו רביעה","v":"315523662","p":"","a":"דריג'את 0, דריג'את","s":0,"t":0,"vo":false,"ci":359},{"o":8186002,"f":"עאישה","l":"ח'טיב","v":"300569795","p":"","a":"דריג'את 0, דריג'את","s":0,"t":0,"vo":false,"ci":359},{"o":9414753,"f":"פהימה","l":"אבו חמאד","v":"035184266","p":"","a":"דריג'את 0, דריג'את","s":0,"t":0,"vo":false,"ci":359},{"o":10696787,"f":"אמינה","l":"מאג'ד","v":"039184973","p":"","a":"דריג'את 0, דריג'את","s":0,"t":0,"vo":false,"ci":359},{"o":13041719,"f":"עבדלכרים","l":"רייט","v":"304809478","p":"","a":"דריג'את 0, דריג'את","s":0,"t":0,"vo":false,"ci":359},{"o":7573633,"f":"סאאד","l":"אבו חמאד","v":"315864256","p":"","a":"דריג'את 0, דריג'את","s":0,"t":0,"vo":false,"ci":359},{"o":11636805,"f":"פאיז","l":"אבו חמאד","v":"040148306","p":"","a":"דריג'את 0, דריג'את","s":0,"t":0,"vo":false,"ci":359},{"o":7571590,"f":"נוזהא","l":"אבו קרינאת","v":"300628435","p":"","a":"דריג'את 0, דריג'את","s":0,"t":0,"vo":false,"ci":359},{"o":10969182,"f":"סעיד","l":"אבו חמאד","v":"027622232","p":"","a":"דריג'את 0, דריג'את","s":0,"t":0,"vo":false,"ci":359},{"o":8865917,"f":"מוחמד","l":"אלרייאט","v":"307895672","p":"","a":"דריג'את 0, דריג'את","s":0,"t":0,"vo":false,"ci":359},{"o":10973277,"f":"איסמאעיל","l":"אבו חמאד","v":"312209935","p":"","a":"דריג'את 0, דריג'את","s":0,"t":0,"vo":false,"ci":359},{"o":9651304,"f":"נורית","l":"אבו חמאד","v":"207217787","p":"","a":"דריג'את 0, דריג'את","s":0,"t":0,"vo":false,"ci":359},{"o":12254648,"f":"נואף","l":"אבו רביעה","v":"026346551","p":"","a":"דריג'את 0, דריג'את","s":0,"t":0,"vo":false,"ci":359},{"o":11678129,"f":"מחמד","l":"אבו רביעה","v":"318944428","p":"","a":"דריג'את 0, דריג'את","s":0,"t":0,"vo":false,"ci":359},{"o":11361707,"f":"פדיה","l":"אלמחאריק","v":"023151269","p":"","a":"דריג'את 0, דריג'את","s":0,"t":0,"vo":false,"ci":359},{"o":12290481,"f":"נסרין","l":"אבו חמאד","v":"315404525","p":"","a":"דריג'את 0, דריג'את","s":0,"t":0,"vo":false,"ci":359},{"o":13554114,"f":"אסלם","l":"אבו חמאד","v":"305550451","p":"","a":"דריג'את 0, דריג'את","s":0,"t":0,"vo":false,"ci":359},{"o":12694991,"f":"עליה","l":"אבו חמאד","v":"059441170","p":"","a":"דריג'את 0, דריג'את","s":0,"t":0,"vo":false,"ci":359},{"o":12005796,"f":"מעזוזה","l":"אבו חמאד","v":"030779995","p":"","a":"דריג'את 0, דריג'את","s":0,"t":0,"vo":false,"ci":359},{"o":11644324,"f":"ג'אמנה","l":"אבו חמאד","v":"312217136","p":"","a":"דריג'את 0, דריג'את","s":0,"t":0,"vo":false,"ci":359},{"o":11887008,"f":"עבד אל רחמן","l":"חאג' עאמר","v":"315613497","p":"","a":"דריג'את 0, דריג'את","s":0,"t":0,"vo":false,"ci":359},{"o":8285544,"f":"אימאן","l":"חאג' עאמר","v":"300418563","p":"","a":"דריג'את 0, דריג'את","s":0,"t":0,"vo":false,"ci":359},{"o":11914665,"f":"סאאב","l":"אבו חמאד","v":"323042499","p":"","a":"דריג'את 0, דריג'את","s":0,"t":0,"vo":false,"ci":359},{"o":12624356,"f":"ביסאן","l":"אבו חאמד","v":"206450215","p":"","a":"דריג'את 0, דריג'את","s":0,"t":0,"vo":false,"ci":359},{"o":10770817,"f":"הדיל","l":"אבו רביעה","v":"206366569","p":"","a":"דריג'את 0, דריג'את","s":0,"t":0,"vo":false,"ci":359},{"o":13278700,"f":"תאמר","l":"אבו רביעה","v":"204704126","p":"","a":"דריג'את 0, דריג'את","s":0,"t":0,"vo":false,"ci":359},{"o":9060773,"f":"רודינה","l":"אבו חמאד","v":"039224431","p":"","a":"דריג'את 0, דריג'את","s":0,"t":0,"vo":false,"ci":359},{"o":12923380,"f":"פאדי","l":"אבו חאמד","v":"208401570","p":"","a":"דריג'את 0, דריג'את","s":0,"t":0,"vo":false,"ci":359},{"o":13518335,"f":"פתחיה","l":"אבו חמאד","v":"026426833","p":"","a":"דריג'את 0, דריג'את","s":0,"t":0,"vo":false,"ci":359},{"o":12059018,"f":"אנואר","l":"אבו רביעה","v":"029243375","p":"","a":"דריג'את 0, דריג'את","s":0,"t":0,"vo":false,"ci":359},{"o":13673955,"f":"מייסם","l":"אבן חמאד","v":"324089952","p":"","a":"דריג'את 0, דריג'את","s":0,"t":0,"vo":false,"ci":359},{"o":13080051,"f":"פאטמה","l":"קבועה","v":"301905675","p":"","a":"דריג'את 0, דריג'את","s":0,"t":0,"vo":false,"ci":359},{"o":9279928,"f":"מרים","l":"ארייט","v":"303330831","p":"","a":"דריג'את 0, דריג'את","s":0,"t":0,"vo":false,"ci":359},{"o":11644292,"f":"מוחמד","l":"אבו רביעה","v":"312217151","p":"","a":"דריג'את 0, דריג'את","s":0,"t":0,"vo":false,"ci":359},{"o":13004282,"f":"פריד","l":"אבו חמאד","v":"203060819","p":"","a":"דריג'את 0, דריג'את","s":0,"t":0,"vo":false,"ci":359},{"o":8628670,"f":"זאהי","l":"אבו רביעה","v":"300578465","p":"","a":"דריג'את 0, דריג'את","s":0,"t":0,"vo":false,"ci":359},{"o":8648126,"f":"מיסרה","l":"אבן חמאד","v":"313623282","p":"","a":"דריג'את 0, דריג'את","s":0,"t":0,"vo":false,"ci":359},{"o":12092807,"f":"עלי","l":"אבו חמאד אלעוודה","v":"308091800","p":"","a":"דריג'את 0, דריג'את","s":0,"t":0,"vo":false,"ci":359},{"o":9102794,"f":"מאהר","l":"אבו חמאד","v":"039226535","p":"","a":"דריג'את 0, דריג'את","s":0,"t":0,"vo":false,"ci":359},{"o":7962941,"f":"אימאן","l":"רייט","v":"206815524","p":"","a":"דריג'את 0, דריג'את","s":0,"t":0,"vo":false,"ci":359},{"o":8313146,"f":"רעיסה","l":"אבו חמאד","v":"204386148","p":"","a":"דריג'את 0, דריג'את","s":0,"t":0,"vo":false,"ci":359},{"o":13870491,"f":"סונדוס","l":"אבו רביעה","v":"305128514","p":"","a":"דריג'את 0, דריג'את","s":0,"t":0,"vo":false,"ci":359},{"o":13978013,"f":"ווהיב","l":"אבו חמאד","v":"204372999","p":"","a":"דריג'את 0, דריג'את","s":0,"t":0,"vo":false,"ci":359},{"o":9574877,"f":"עימאד אלדין","l":"אבו רביעה","v":"305370132","p":"","a":"דריג'את 0, דריג'את","s":0,"t":0,"vo":false,"ci":359},{"o":9294301,"f":"מועאד'","l":"חאג' עאמר","v":"205608581","p":"","a":"דריג'את 0, דריג'את","s":0,"t":0,"vo":false,"ci":359},{"o":13865349,"f":"מועאוויה","l":"חאג' עאמר","v":"212571335","p":"","a":"דריג'את 0, דריג'את","s":0,"t":0,"vo":false,"ci":359},{"o":9049555,"f":"עאוני","l":"אבו חמאד","v":"211704374","p":"","a":"דריג'את 0, דריג'את","s":0,"t":0,"vo":false,"ci":359},{"o":10454470,"f":"מחמוד","l":"אלעואודה","v":"326910320","p":"","a":"דריג'את 0, דריג'את","s":0,"t":0,"vo":false,"ci":359},{"o":11615720,"f":"עקרם","l":"אבו רביעה","v":"060681087","p":"","a":"דריג'את 0, דריג'את","s":0,"t":0,"vo":false,"ci":359},{"o":8798682,"f":"אן","l":"אבו רביעה","v":"209390822","p":"","a":"דריג'את 0, דריג'את","s":0,"t":0,"vo":false,"ci":359},{"o":10075589,"f":"נאיף","l":"אבו חמאד","v":"058974643","p":"","a":"דריג'את 0, דריג'את","s":0,"t":0,"vo":false,"ci":359},{"o":11290096,"f":"אינשראח","l":"אבו חמאד","v":"300674017","p":"","a":"דריג'את 0, דריג'את","s":0,"t":0,"vo":false,"ci":359},{"o":7883033,"f":"מועין","l":"אבו חמאד","v":"313129306","p":"","a":"דריג'את 0, דריג'את","s":0,"t":0,"vo":false,"ci":359},{"o":7682327,"f":"אקרם","l":"אבו חמאד אלעוודה","v":"032971467","p":"","a":"דריג'את 0, דריג'את","s":0,"t":0,"vo":false,"ci":359},{"o":7874844,"f":"איוב","l":"אבו-חמאד אלעוודה","v":"313129850","p":"","a":"דריג'את 0, דריג'את","s":0,"t":0,"vo":false,"ci":359},{"o":11214286,"f":"יעקב","l":"אבו חמאד","v":"053838694","p":"","a":"דריג'את 0, דריג'את","s":0,"t":0,"vo":false,"ci":359},{"o":13421994,"f":"רים","l":"אבו חמאד","v":"311375422","p":"","a":"דריג'את 0, דריג'את","s":0,"t":0,"vo":false,"ci":359},{"o":12005853,"f":"בהא","l":"אבו חמאד","v":"307849927","p":"","a":"דריג'את 0, דריג'את","s":0,"t":0,"vo":false,"ci":359},{"o":9444859,"f":"עוודללה","l":"אבו חמאד","v":"027694793","p":"","a":"דריג'את 0, דריג'את","s":0,"t":0,"vo":false,"ci":359},{"o":12393936,"f":"פתחי","l":"אבן חמאד","v":"032941213","p":"","a":"דריג'את 0, דריג'את","s":0,"t":0,"vo":false,"ci":359},{"o":13387196,"f":"תמאם","l":"אבו חמאד","v":"059519801","p":"","a":"דריג'את 0, דריג'את","s":0,"t":0,"vo":false,"ci":359},{"o":9155066,"f":"קוקב","l":"אבו חמאד אלעוודה","v":"037774866","p":"","a":"דריג'את 0, דריג'את","s":0,"t":0,"vo":false,"ci":359},{"o":8617462,"f":"עליה","l":"אבו חמאד","v":"066447913","p":"","a":"דריג'את 0, דריג'את","s":0,"t":0,"vo":false,"ci":359},{"o":11878848,"f":"קייס","l":"אבו רביעה","v":"318885613","p":"","a":"דריג'את 0, דריג'את","s":0,"t":0,"vo":false,"ci":359},{"o":8373512,"f":"עלי","l":"אבו חמאד","v":"201485596","p":"","a":"דריג'את 0, דריג'את","s":0,"t":0,"vo":false,"ci":359},{"o":10076641,"f":"קאמלה","l":"אבו רביעה","v":"058974585","p":"","a":"דריג'את 0, דריג'את","s":0,"t":0,"vo":false,"ci":359},{"o":10430951,"f":"אמל","l":"אבו חמאד","v":"206422263","p":"","a":"דריג'את 0, דריג'את","s":0,"t":0,"vo":false,"ci":359},{"o":10807772,"f":"עייש","l":"אבו רביעה","v":"029164324","p":"","a":"דריג'את 0, דריג'את","s":0,"t":0,"vo":false,"ci":359},{"o":11170258,"f":"רמי","l":"אבו חמאד","v":"315603936","p":"","a":"דריג'את 0, דריג'את","s":0,"t":0,"vo":false,"ci":359},{"o":10137062,"f":"קותיבה","l":"ארייט","v":"315809657","p":"","a":"דריג'את 0, דריג'את","s":0,"t":0,"vo":false,"ci":359},{"o":11134421,"f":"עטיה","l":"אבן חמאד","v":"204332563","p":"","a":"דריג'את 0, דריג'את","s":0,"t":0,"vo":false,"ci":359},{"o":10075622,"f":"יוסף","l":"אבו חמאד","v":"058974635","p":"","a":"דריג'את 0, דריג'את","s":0,"t":0,"vo":false,"ci":359},{"o":9086217,"f":"שריף","l":"אבו חמאד","v":"032495541","p":"","a":"דריג'את 0, דריג'את","s":0,"t":0,"vo":false,"ci":359},{"o":9412874,"f":"אחמד","l":"חאג' עאמר","v":"037283827","p":"","a":"דריג'את 0, דריג'את","s":0,"t":0,"vo":false,"ci":359},{"o":8175098,"f":"השאם","l":"אבו חמאד","v":"066714049","p":"","a":"דריג'את 0, דריג'את","s":0,"t":0,"vo":false,"ci":359},{"o":11779381,"f":"מיאר","l":"אבו כרש","v":"207244559","p":"","a":"דריג'את 0, דריג'את","s":0,"t":0,"vo":false,"ci":359},{"o":12641607,"f":"זינאד","l":"אבו רביעה","v":"031435605","p":"","a":"דריג'את 0, דריג'את","s":0,"t":0,"vo":false,"ci":359},{"o":11885885,"f":"היתם","l":"אבן חמאד","v":"315613653","p":"","a":"דריג'את 0, דריג'את","s":0,"t":0,"vo":false,"ci":359},{"o":12474678,"f":"עבדאללה","l":"אבו רביעה","v":"037237112","p":"","a":"דריג'את 0, דריג'את","s":0,"t":0,"vo":false,"ci":359},{"o":11190560,"f":"זריפה","l":"אבו חמאד","v":"053838603","p":"","a":"דריג'את 0, דריג'את","s":0,"t":0,"vo":false,"ci":359},{"o":11946300,"f":"יאסר","l":"אבו חמאד","v":"027575430","p":"","a":"דריג'את 0, דריג'את","s":0,"t":0,"vo":false,"ci":359},{"o":10667311,"f":"עבאס","l":"אבו רביעה","v":"208895888","p":"","a":"דריג'את 0, דריג'את","s":0,"t":0,"vo":false,"ci":359},{"o":10524974,"f":"נסרי","l":"אבו רביעה","v":"059412114","p":"","a":"דריג'את 0, דריג'את","s":0,"t":0,"vo":false,"ci":359},{"o":11248933,"f":"יחיא","l":"אבו חמאד","v":"201092186","p":"","a":"דריג'את 0, דריג'את","s":0,"t":0,"vo":false,"ci":359},{"o":11619647,"f":"סמאח","l":"אבו חמאד","v":"205576200","p":"","a":"דריג'את 0, דריג'את","s":0,"t":0,"vo":false,"ci":359},{"o":12236075,"f":"אסרא","l":"אבו חאמד","v":"315402271","p":"","a":"דריג'את 0, דריג'את","s":0,"t":0,"vo":false,"ci":359},{"o":9969930,"f":"אריג'","l":"אלרייאט","v":"324036920","p":"","a":"דריג'את 0, דריג'את","s":0,"t":0,"vo":false,"ci":359},{"o":10059018,"f":"עווד","l":"אבו חמאד","v":"209197185","p":"","a":"דריג'את 0, דריג'את","s":0,"t":0,"vo":false,"ci":359},{"o":12491053,"f":"נוסיבה","l":"אבו רביעה","v":"204418099","p":"","a":"דריג'את 0, דריג'את","s":0,"t":0,"vo":false,"ci":359},{"o":13437273,"f":"סוהילה","l":"דריגאת","v":"207549429","p":"","a":"דריג'את 0, דריג'את","s":0,"t":0,"vo":false,"ci":359},{"o":13918529,"f":"איברהים","l":"אבו חמאד","v":"065901092","p":"","a":"דריג'את 0, דריג'את","s":0,"t":0,"vo":false,"ci":359},{"o":9826574,"f":"עאן","l":"אבן חמאד","v":"043178227","p":"","a":"דריג'את 0, דריג'את","s":0,"t":0,"vo":false,"ci":359},{"o":8563998,"f":"אמוני","l":"אבו חמאד","v":"066445404","p":"","a":"דריג'את 0, דריג'את","s":0,"t":0,"vo":false,"ci":359},{"o":13726029,"f":"נעים","l":"אבו חמאד","v":"206250490","p":"","a":"דריג'את 0, דריג'את","s":0,"t":0,"vo":false,"ci":359},{"o":7664084,"f":"תמאם","l":"אבו רביעה","v":"055764377","p":"","a":"דריג'את 0, דריג'את","s":0,"t":0,"vo":false,"ci":359},{"o":8201692,"f":"חמידאן","l":"אבו חמאד","v":"312191257","p":"","a":"דריג'את 0, דריג'את","s":0,"t":0,"vo":false,"ci":359},{"o":8775975,"f":"הנייה","l":"אבו חמאד","v":"028333391","p":"","a":"דריג'את 0, דריג'את","s":0,"t":0,"vo":false,"ci":359},{"o":12888422,"f":"שיראן","l":"אבו חמאד","v":"300609278","p":"","a":"דריג'את 0, דריג'את","s":0,"t":0,"vo":false,"ci":359},{"o":9436460,"f":"טארק","l":"אבו חמאד","v":"207368085","p":"","a":"דריג'את 0, דריג'את","s":0,"t":0,"vo":false,"ci":359},{"o":9553204,"f":"עמאד","l":"אבן חמאד","v":"037288974","p":"","a":"דריג'את 0, דריג'את","s":0,"t":0,"vo":false,"ci":359},{"o":12477721,"f":"יוסרא","l":"אבו חמאד","v":"030414619","p":"","a":"דריג'את 0, דריג'את","s":0,"t":0,"vo":false,"ci":359},{"o":10045745,"f":"נג'א","l":"אבן חמאד","v":"324037910","p":"","a":"דריג'את 0, דריג'את","s":0,"t":0,"vo":false,"ci":359},{"o":11815196,"f":"אמנה","l":"אבו חמאד","v":"032937666","p":"","a":"דריג'את 0, דריג'את","s":0,"t":0,"vo":false,"ci":359},{"o":11019524,"f":"כאיד","l":"אבו חמאד","v":"027625110","p":"","a":"דריג'את 0, דריג'את","s":0,"t":0,"vo":false,"ci":359},{"o":8485164,"f":"חדרה","l":"אבו חמאד","v":"050123686","p":"","a":"דריג'את 0, דריג'את","s":0,"t":0,"vo":false,"ci":359},{"o":10777867,"f":"סברין","l":"אבו חמאד","v":"209481738","p":"","a":"דריג'את 0, דריג'את","s":0,"t":0,"vo":false,"ci":359},{"o":11215131,"f":"ניזאר","l":"אבו רביעה","v":"313166027","p":"","a":"דריג'את 0, דריג'את","s":0,"t":0,"vo":false,"ci":359},{"o":9433406,"f":"מרים","l":"אבו חאמד","v":"035188549","p":"","a":"דריג'את 0, דריג'את","s":0,"t":0,"vo":false,"ci":359},{"o":12578062,"f":"כפאיה","l":"אבו חמאד","v":"322745217","p":"","a":"דריג'את 0, דריג'את","s":0,"t":0,"vo":false,"ci":359},{"o":12975476,"f":"מחמד","l":"אבו רביעה","v":"211605084","p":"","a":"דריג'את 0, דריג'את","s":0,"t":0,"vo":false,"ci":359},{"o":13155707,"f":"מרים","l":"אבו חמאד","v":"039778972","p":"","a":"דריג'את 0, דריג'את","s":0,"t":0,"vo":false,"ci":359},{"o":13227377,"f":"חמזה","l":"חאג' עאמר","v":"204427264","p":"","a":"דריג'את 0, דריג'את","s":0,"t":0,"vo":false,"ci":359},{"o":11796750,"f":"חאתם","l":"אבו חמאד","v":"033241498","p":"","a":"דריג'את 0, דריג'את","s":0,"t":0,"vo":false,"ci":359},{"o":8803645,"f":"וסאם","l":"אבו חמאד","v":"323861658","p":"","a":"דריג'את 0, דריג'את","s":0,"t":0,"vo":false,"ci":359},{"o":12609915,"f":"אמין","l":"רייט","v":"313185423","p":"","a":"דריג'את 0, דריג'את","s":0,"t":0,"vo":false,"ci":359},{"o":9932074,"f":"אדם","l":"אבו חמאד","v":"209257062","p":"","a":"דריג'את 0, דריג'את","s":0,"t":0,"vo":false,"ci":359},{"o":9365839,"f":"האנה","l":"אבו חמאד","v":"066458571","p":"","a":"דריג'את 0, דריג'את","s":0,"t":0,"vo":false,"ci":359},{"o":7654833,"f":"עבס","l":"אבו רביעה","v":"305410102","p":"","a":"דריג'את 0, דריג'את","s":0,"t":0,"vo":false,"ci":359},{"o":12293500,"f":"סאלוה","l":"אל מחאריק","v":"029895141","p":"","a":"דריג'את 0, דריג'את","s":0,"t":0,"vo":false,"ci":359},{"o":10705259,"f":"מראם","l":"אבו חאמד","v":"208898130","p":"","a":"דריג'את 0, דריג'את","s":0,"t":0,"vo":false,"ci":359},{"o":11187552,"f":"סמר","l":"אבו חמאד","v":"307835496","p":"","a":"דריג'את 0, דריג'את","s":0,"t":0,"vo":false,"ci":359},{"o":7553464,"f":"עלי","l":"אבו רביעה","v":"054467261","p":"","a":"דריג'את 0, דריג'את","s":0,"t":0,"vo":false,"ci":359},{"o":9970005,"f":"עאמר","l":"חאג' עאמר","v":"056872930","p":"","a":"דריג'את 0, דריג'את","s":0,"t":0,"vo":false,"ci":359},{"o":8979783,"f":"עאדל","l":"אבו רביעה","v":"211700158","p":"","a":"דריג'את 0, דריג'את","s":0,"t":0,"vo":false,"ci":359},{"o":11024743,"f":"הרון","l":"חאג' עאמר","v":"066601139","p":"","a":"דריג'את 0, דריג'את","s":0,"t":0,"vo":false,"ci":359},{"o":10521968,"f":"נסרה","l":"אבו רביעה","v":"059412635","p":"","a":"דריג'את 0, דריג'את","s":0,"t":0,"vo":false,"ci":359},{"o":11970919,"f":"אמין","l":"אבו חמאד","v":"029240371","p":"","a":"דריג'את 0, דריג'את","s":0,"t":0,"vo":false,"ci":359},{"o":8658262,"f":"ודאעה","l":"אבו חמאד","v":"322843392","p":"","a":"דריג'את 0, דריג'את","s":0,"t":0,"vo":false,"ci":359},{"o":13198621,"f":"סמר","l":"אבו חמאד","v":"307861039","p":"","a":"דריג'את 0, דריג'את","s":0,"t":0,"vo":false,"ci":359},{"o":11992417,"f":"נסר","l":"אבו רביעה","v":"027578061","p":"","a":"דריג'את 0, דריג'את","s":0,"t":0,"vo":false,"ci":359},{"o":7617964,"f":"צאלח","l":"אבו חמאד","v":"035162502","p":"","a":"דריג'את 0, דריג'את","s":0,"t":0,"vo":false,"ci":359},{"o":10093891,"f":"ונוס","l":"אבו רביעה","v":"315806745","p":"","a":"דריג'את 0, דריג'את","s":0,"t":0,"vo":false,"ci":359},{"o":12471653,"f":"ראדה","l":"אבו חמאד","v":"037236080","p":"","a":"דריג'את 0, דריג'את","s":0,"t":0,"vo":false,"ci":359},{"o":12194150,"f":"עלוא","l":"אבן חמאד","v":"211686571","p":"","a":"דריג'את 0, דריג'את","s":0,"t":0,"vo":false,"ci":359},{"o":13780238,"f":"וואסים","l":"אבו חמאד","v":"203416680","p":"","a":"דריג'את 0, דריג'את","s":0,"t":0,"vo":false,"ci":359},{"o":8800603,"f":"דינה","l":"אבו רביעה","v":"028334415","p":"","a":"דריג'את 0, דריג'את","s":0,"t":0,"vo":false,"ci":359},{"o":11268469,"f":"סוג'וד","l":"חאג' עאמר","v":"315540625","p":"","a":"דריג'את 0, דריג'את","s":0,"t":0,"vo":false,"ci":359},{"o":13633806,"f":"פאתן","l":"אבו חמאד","v":"303020648","p":"","a":"דריג'את 0, דריג'את","s":0,"t":0,"vo":false,"ci":359},{"o":9615730,"f":"דועא","l":"חאג' עאמר","v":"207215518","p":"","a":"דריג'את 0, דריג'את","s":0,"t":0,"vo":false,"ci":359},{"o":11006273,"f":"אנצאף","l":"אבו חמאד","v":"304717267","p":"","a":"דריג'את 0, דריג'את","s":0,"t":0,"vo":false,"ci":359},{"o":13966654,"f":"ראלייה","l":"אבו רביעה","v":"037969714","p":"","a":"דריג'את 0, דריג'את","s":0,"t":0,"vo":false,"ci":359},{"o":9222496,"f":"מנאר","l":"אבו כרש","v":"205606536","p":"","a":"דריג'את 0, דריג'את","s":0,"t":0,"vo":false,"ci":359},{"o":8163730,"f":"פאטמה","l":"אבו חמאד","v":"037971702","p":"","a":"דריג'את 0, דריג'את","s":0,"t":0,"vo":false,"ci":359},{"o":8080779,"f":"מהאדי","l":"אבו רביעה","v":"322618117","p":"","a":"דריג'את 0, דריג'את","s":0,"t":0,"vo":false,"ci":359},{"o":8783223,"f":"יזיד","l":"אבן חמאד","v":"322413907","p":"","a":"דריג'את 0, דריג'את","s":0,"t":0,"vo":false,"ci":359},{"o":11583809,"f":"שאדי","l":"אבו חמאד","v":"305461063","p":"","a":"דריג'את 0, דריג'את","s":0,"t":0,"vo":false,"ci":359},{"o":9317757,"f":"לואי","l":"אבו חמאד","v":"315452318","p":"","a":"דריג'את 0, דריג'את","s":0,"t":0,"vo":false,"ci":359},{"o":7831938,"f":"סאוסן","l":"אבו רביעה","v":"036468288","p":"","a":"דריג'את 0, דריג'את","s":0,"t":0,"vo":false,"ci":359},{"o":10213741,"f":"הודא","l":"אבו חמאד","v":"301801114","p":"","a":"דריג'את 0, דריג'את","s":0,"t":0,"vo":false,"ci":359},{"o":8188299,"f":"אמג'ד","l":"אבו רביעה","v":"318275062","p":"","a":"דריג'את 0, דריג'את","s":0,"t":0,"vo":false,"ci":359},{"o":12520775,"f":"אמינה","l":"אבו חמאד","v":"030780472","p":"","a":"דריג'את 0, דריג'את","s":0,"t":0,"vo":false,"ci":359},{"o":9426294,"f":"שאפי","l":"אבו חמאד","v":"025939067","p":"","a":"דריג'את 0, דריג'את","s":0,"t":0,"vo":false,"ci":359},{"o":12130628,"f":"לטיפה","l":"אבו חמאד אלעוודה","v":"035628510","p":"","a":"דריג'את 0, דריג'את","s":0,"t":0,"vo":false,"ci":359},{"o":13496627,"f":"עלי","l":"אבו חמאד","v":"057633752","p":"","a":"דריג'את 0, דריג'את","s":0,"t":0,"vo":false,"ci":359},{"o":13359818,"f":"מוסה","l":"חאג' עאמר","v":"300059326","p":"","a":"דריג'את 0, דריג'את","s":0,"t":0,"vo":false,"ci":359},{"o":13722323,"f":"איאד","l":"אבו חמאד","v":"300831799","p":"","a":"דריג'את 0, דריג'את","s":0,"t":0,"vo":false,"ci":359},{"o":13711062,"f":"אסיל","l":"אבו רביעה","v":"211616362","p":"","a":"דריג'את 0, דריג'את","s":0,"t":0,"vo":false,"ci":359},{"o":11597501,"f":"פתחיה","l":"אבו חאמד","v":"058561218","p":"","a":"דריג'את 0, דריג'את","s":0,"t":0,"vo":false,"ci":359},{"o":13291207,"f":"האני","l":"אבו רביעה","v":"039349881","p":"","a":"דריג'את 0, דריג'את","s":0,"t":0,"vo":false,"ci":359},{"o":11533984,"f":"אסמעיל","l":"אבו חמאד","v":"046229290","p":"","a":"דריג'את 0, דריג'את","s":0,"t":0,"vo":false,"ci":359},{"o":13788866,"f":"מונתהא","l":"אבו חמאד","v":"316507144","p":"","a":"דריג'את 0, דריג'את","s":0,"t":0,"vo":false,"ci":359},{"o":10870455,"f":"רים","l":"אבו חמאד","v":"204481956","p":"","a":"דריג'את 0, דריג'את","s":0,"t":0,"vo":false,"ci":359},{"o":12022437,"f":"פאטמה","l":"אבו חמאד","v":"029242906","p":"","a":"דריג'את 0, דריג'את","s":0,"t":0,"vo":false,"ci":359},{"o":13528790,"f":"וופא","l":"אבו חמאד","v":"046251518","p":"","a":"דריג'את 0, דריג'את","s":0,"t":0,"vo":false,"ci":359},{"o":7550569,"f":"נאדר","l":"אבו חמאד","v":"315861195","p":"","a":"דריג'את 0, דריג'את","s":0,"t":0,"vo":false,"ci":359},{"o":10876549,"f":"נעמה","l":"אבו חמאד","v":"011738267","p":"","a":"דריג'את 0, דריג'את","s":0,"t":0,"vo":false,"ci":359},{"o":8363614,"f":"מחמוד","l":"אבו חמאד","v":"028266732","p":"","a":"דריג'את 0, דריג'את","s":0,"t":0,"vo":false,"ci":359},{"o":12632802,"f":"וולא","l":"אבו חמאד","v":"315994574","p":"","a":"דריג'את 14, דריג'את","s":0,"t":0,"vo":false,"ci":359},{"o":11787925,"f":"ביאן","l":"אבו חמאד","v":"315059220","p":"","a":"דריג'את 0, דריג'את","s":0,"t":0,"vo":false,"ci":359},{"o":9368231,"f":"אובאי","l":"חאג' שאקר","v":"203720891","p":"","a":"דריג'את 0, דריג'את","s":0,"t":0,"vo":false,"ci":359},{"o":9393828,"f":"עלי","l":"אבו ארביעה","v":"066459694","p":"","a":"דריג'את 0, דריג'את","s":0,"t":0,"vo":false,"ci":359},{"o":13680379,"f":"למיס","l":"אבו חמאד","v":"324089135","p":"","a":"דריג'את 0, דריג'את","s":0,"t":0,"vo":false,"ci":359},{"o":8795817,"f":"חדאר","l":"אבו חמאד","v":"301873238","p":"","a":"דריג'את 0, דריג'את","s":0,"t":0,"vo":false,"ci":359},{"o":13735650,"f":"פאטמה","l":"אבו חמאד","v":"035218296","p":"","a":"דריג'את 0, דריג'את","s":0,"t":0,"vo":false,"ci":359},{"o":13796070,"f":"מנסור","l":"אבו חמאד","v":"026210468","p":"","a":"דריג'את 0, דריג'את","s":0,"t":0,"vo":false,"ci":359},{"o":12416651,"f":"נוהה","l":"אבו כרש","v":"028383875","p":"","a":"דריג'את 0, דריג'את","s":0,"t":0,"vo":false,"ci":359},{"o":12697335,"f":"שאפה","l":"אבו חמאד","v":"026139311","p":"","a":"דריג'את 0, דריג'את","s":0,"t":0,"vo":false,"ci":359},{"o":10439332,"f":"ראניה","l":"אבו חאמד","v":"316059468","p":"","a":"דריג'את 0, דריג'את","s":0,"t":0,"vo":false,"ci":359},{"o":10521244,"f":"עישה","l":"אבו חמאד","v":"059412551","p":"","a":"דריג'את 0, דריג'את","s":0,"t":0,"vo":false,"ci":359},{"o":10453665,"f":"רג'א","l":"אבו חמאד","v":"326910239","p":"","a":"דריג'את 0, דריג'את","s":0,"t":0,"vo":false,"ci":359},{"o":10870426,"f":"ספא","l":"חאג' עאמר","v":"305451254","p":"","a":"דריג'את 0, דריג'את","s":0,"t":0,"vo":false,"ci":359},{"o":9321167,"f":"בסאם","l":"אבן חמאד","v":"027690338","p":"","a":"דריג'את 0, דריג'את","s":0,"t":0,"vo":false,"ci":359},{"o":11561713,"f":"גודאת","l":"אבו רביעה","v":"200297653","p":"","a":"דריג'את 0, דריג'את","s":0,"t":0,"vo":false,"ci":359},{"o":10145500,"f":"פהימה","l":"אבו חמאד","v":"305509200","p":"","a":"דריג'את 0, דריג'את","s":0,"t":0,"vo":false,"ci":359},{"o":13798041,"f":"אסמא","l":"אבו רביעה","v":"300833225","p":"","a":"דריג'את 0, דריג'את","s":0,"t":0,"vo":false,"ci":359},{"o":8363571,"f":"סאלם","l":"אבו חמאד","v":"028266773","p":"","a":"דריג'את 0, דריג'את","s":0,"t":0,"vo":false,"ci":359},{"o":8172082,"f":"תהאני","l":"אבו חמאד","v":"066713421","p":"","a":"דריג'את 0, דריג'את","s":0,"t":0,"vo":false,"ci":359},{"o":11246335,"f":"ראודה","l":"אבו רביעה","v":"026486142","p":"","a":"דריג'את 0, דריג'את","s":0,"t":0,"vo":false,"ci":359},{"o":7564843,"f":"הודא","l":"חאג' עאמר","v":"315589028","p":"","a":"דריג'את 0, דריג'את","s":0,"t":0,"vo":false,"ci":359},{"o":8841950,"f":"חאפסא","l":"אבו חמאד","v":"300794187","p":"","a":"דריג'את 0, דריג'את","s":0,"t":0,"vo":false,"ci":359},{"o":10366663,"f":"יסמין","l":"אלשיך","v":"205773310","p":"","a":"דריג'את 0, דריג'את","s":0,"t":0,"vo":false,"ci":359},{"o":10803966,"f":"אמאל","l":"אבו חמאד","v":"029164720","p":"","a":"דריג'את 0, דריג'את","s":0,"t":0,"vo":false,"ci":359},{"o":8028705,"f":"חיתאם","l":"דריגאת","v":"211342621","p":"","a":"דריג'את 0, דריג'את","s":0,"t":0,"vo":false,"ci":359},{"o":13474454,"f":"תגריד","l":"אבו חמאד","v":"302092150","p":"","a":"דריג'את 0, דריג'את","s":0,"t":0,"vo":false,"ci":359},{"o":7986725,"f":"וורוד","l":"אבו רביעה","v":"315922500","p":"","a":"דריג'את 0, דריג'את","s":0,"t":0,"vo":false,"ci":359},{"o":10770168,"f":"ואיל","l":"אבו חמאד","v":"301252177","p":"","a":"דריג'את 0, דריג'את","s":0,"t":0,"vo":false,"ci":359},{"o":9005780,"f":"אמינה","l":"חאג' עאמר","v":"203590682","p":"","a":"דריג'את 0, דריג'את","s":0,"t":0,"vo":false,"ci":359},{"o":11074293,"f":"יצחק","l":"אבו חמאד","v":"052474616","p":"","a":"דריג'את 0, דריג'את","s":0,"t":0,"vo":false,"ci":359},{"o":9576140,"f":"קאמל","l":"אבו רביעה","v":"052452794","p":"","a":"דריג'את 0, דריג'את","s":0,"t":0,"vo":false,"ci":359},{"o":13300387,"f":"רומל","l":"דריג'את","v":"316006485","p":"","a":"דריג'את 0, דריג'את","s":0,"t":0,"vo":false,"ci":359},{"o":12688046,"f":"דוניה","l":"אבו חמאד","v":"066563057","p":"","a":"דריג'את 0, דריג'את","s":0,"t":0,"vo":false,"ci":359},{"o":8767222,"f":"דינה","l":"אבו חמאד","v":"027687821","p":"","a":"דריג'את 0, דריג'את","s":0,"t":0,"vo":false,"ci":359},{"o":12752565,"f":"אינת","l":"אבו רביעה","v":"061999157","p":"","a":"דריג'את 0, דריג'את","s":0,"t":0,"vo":false,"ci":359},{"o":13364914,"f":"פאטמה","l":"אבו רביעה","v":"204640031","p":"","a":"דריג'את 0, דריג'את","s":0,"t":0,"vo":false,"ci":359},{"o":11702984,"f":"נאהד","l":"אבו חמאד","v":"301820791","p":"","a":"דריג'את 0, דריג'את","s":0,"t":0,"vo":false,"ci":359},{"o":13060795,"f":"נארג'יס","l":"אבו חמאד","v":"036936524","p":"","a":"דריג'את 0, דריג'את","s":0,"t":0,"vo":false,"ci":359},{"o":13505200,"f":"האני","l":"אבו חמאד","v":"322329012","p":"","a":"דריג'את 0, דריג'את","s":0,"t":0,"vo":false,"ci":359},{"o":9433840,"f":"מחמד","l":"אבו חמאד","v":"035188564","p":"","a":"דריג'את 0, דריג'את","s":0,"t":0,"vo":false,"ci":359},{"o":10533599,"f":"מחמד","l":"אבו חאמד","v":"205779416","p":"","a":"דריג'את 0, דריג'את","s":0,"t":0,"vo":false,"ci":359},{"o":13263435,"f":"רמאס","l":"אבן חמאד","v":"208282087","p":"","a":"דריג'את 0, דריג'את","s":0,"t":0,"vo":false,"ci":359},{"o":13785683,"f":"אסיל","l":"אבו חמאד","v":"212633689","p":"","a":"דריג'את 0, דריג'את","s":0,"t":0,"vo":false,"ci":359},{"o":10459676,"f":"תאבת","l":"אבו חמאד","v":"207872383","p":"","a":"דריג'את 0, דריג'את","s":0,"t":0,"vo":false,"ci":359},{"o":11336239,"f":"פרידה","l":"אבו חמאד","v":"050870732","p":"","a":"דריג'את 0, דריג'את","s":0,"t":0,"vo":false,"ci":359},{"o":11627058,"f":"חוסאם","l":"אבו חמאד","v":"318667813","p":"","a":"דריג'את 0, דריג'את","s":0,"t":0,"vo":false,"ci":359},{"o":13666907,"f":"נסרין","l":"אבו רביעה","v":"209154103","p":"","a":"דריג'את 0, דריג'את","s":0,"t":0,"vo":false,"ci":359},{"o":11774525,"f":"ואסים","l":"אבו רביעה","v":"207244054","p":"","a":"דריג'את 0, דריג'את","s":0,"t":0,"vo":false,"ci":359},{"o":8235762,"f":"ראג'ה","l":"אבו חמאד","v":"037976123","p":"","a":"דריג'את 0, דריג'את","s":0,"t":0,"vo":false,"ci":359},{"o":10468880,"f":"דועא","l":"אבו חמאד","v":"207873233","p":"","a":"דריג'את 0, דריג'את","s":0,"t":0,"vo":false,"ci":359},{"o":8905233,"f":"סחר","l":"אבו חמאד","v":"315388108","p":"","a":"דריג'את 0, דריג'את","s":0,"t":0,"vo":false,"ci":359},{"o":13950530,"f":"יוסרה","l":"אבן חמאד","v":"026216986","p":"","a":"דריג'את 0, דריג'את","s":0,"t":0,"vo":false,"ci":359},{"o":8170212,"f":"סולטאן","l":"ארייט","v":"025915992","p":"","a":"דריג'את 0, דריג'את","s":0,"t":0,"vo":false,"ci":359},{"o":8677918,"f":"עליה","l":"אבו רביעה","v":"060640570","p":"","a":"דריג'את 0, דריג'את","s":0,"t":0,"vo":false,"ci":359},{"o":11615790,"f":"אמיר","l":"אבו רביעה","v":"060681079","p":"","a":"דריג'את 0, דריג'את","s":0,"t":0,"vo":false,"ci":359},{"o":13622895,"f":"מעתז","l":"אבו חמאד","v":"324087667","p":"","a":"דריג'את 0, דריג'את","s":0,"t":0,"vo":false,"ci":359},{"o":9905712,"f":"תאמר","l":"אבו רביעה","v":"209258482","p":"","a":"דריג'את 0, דריג'את","s":0,"t":0,"vo":false,"ci":359},{"o":9707068,"f":"זיינב","l":"אבו חמאד","v":"043174184","p":"","a":"דריג'את 0, דריג'את","s":0,"t":0,"vo":false,"ci":359},{"o":8830509,"f":"הגר","l":"חאג' עאמר","v":"301509840","p":"","a":"דריג'את 0, דריג'את","s":0,"t":0,"vo":false,"ci":359},{"o":9574975,"f":"סלימאן","l":"אבו חמאד","v":"052452901","p":"","a":"דריג'את 0, דריג'את","s":0,"t":0,"vo":false,"ci":359},{"o":8199885,"f":"עבד רחמאן","l":"אבו חמאד","v":"036959344","p":"","a":"דריג'את 0, דריג'את","s":0,"t":0,"vo":false,"ci":359},{"o":11535873,"f":"זהור","l":"אבו חמאד","v":"204556351","p":"","a":"דריג'את 0, דריג'את","s":0,"t":0,"vo":false,"ci":359},{"o":13216376,"f":"נידל","l":"אבו חמאד","v":"302583133","p":"","a":"דריג'את 0, דריג'את","s":0,"t":0,"vo":false,"ci":359},{"o":8565297,"f":"מוסה","l":"אבו חמאד","v":"035171305","p":"","a":"דריג'את 0, דריג'את","s":0,"t":0,"vo":false,"ci":359},{"o":10538516,"f":"תאמר","l":"אבן חמאד","v":"209264324","p":"","a":"דריג'את 0, דריג'את","s":0,"t":0,"vo":false,"ci":359},{"o":7682752,"f":"שריפה","l":"אבו רביעה","v":"200247914","p":"","a":"דריג'את 0, דריג'את","s":0,"t":0,"vo":false,"ci":359},{"o":8722995,"f":"מונטהא","l":"אבו רביעה","v":"316464932","p":"","a":"דריג'את 0, דריג'את","s":0,"t":0,"vo":false,"ci":359},{"o":8020675,"f":"ניבאל","l":"אבן חמאד","v":"315924282","p":"","a":"דריג'את 0, דריג'את","s":0,"t":0,"vo":false,"ci":359},{"o":9671210,"f":"מחמד","l":"אבו רביעה","v":"059557280","p":"","a":"דריג'את 0, דריג'את","s":0,"t":0,"vo":false,"ci":359},{"o":9250352,"f":"עלא","l":"אבו חמאד","v":"203441902","p":"","a":"דריג'את 0, דריג'את","s":0,"t":0,"vo":false,"ci":359},{"o":13438576,"f":"מייסון","l":"אבו חמאד","v":"208907170","p":"","a":"דריג'את 0, דריג'את","s":0,"t":0,"vo":false,"ci":359},{"o":10267229,"f":"לינה","l":"אבו חמאד","v":"304799828","p":"","a":"דריג'את 0, דריג'את","s":0,"t":0,"vo":false,"ci":359},{"o":10609251,"f":"חיאת","l":"אבו חמאד","v":"207169566","p":"","a":"דריג'את 0, דריג'את","s":0,"t":0,"vo":false,"ci":359},{"o":10459739,"f":"איזאר","l":"אסעד חאג' עאמר","v":"302481767","p":"","a":"דריג'את 0, דריג'את","s":0,"t":0,"vo":false,"ci":359},{"o":9449046,"f":"נאסר","l":"אבו חמאד","v":"027694603","p":"","a":"דריג'את 0, דריג'את","s":0,"t":0,"vo":false,"ci":359},{"o":12614154,"f":"עודאי","l":"אבו חמאד","v":"206518516","p":"","a":"דריג'את 0, דריג'את","s":0,"t":0,"vo":false,"ci":359},{"o":10770031,"f":"רואן","l":"אבו חמאד","v":"206366452","p":"","a":"דריג'את 0, דריג'את","s":0,"t":0,"vo":false,"ci":359},{"o":8728139,"f":"נאז'יה","l":"אבו רביעה","v":"300146495","p":"","a":"דריג'את 0, דריג'את","s":0,"t":0,"vo":false,"ci":359},{"o":13416962,"f":"ראהג","l":"אלרואשדה","v":"042829655","p":"","a":"דריג'את 0, דריג'את","s":0,"t":0,"vo":false,"ci":359},{"o":8363695,"f":"חדר","l":"אבו רביעה","v":"028266724","p":"","a":"דריג'את 0, דריג'את","s":0,"t":0,"vo":false,"ci":359},{"o":10075720,"f":"סלים","l":"אבו חמאד","v":"058974676","p":"","a":"דריג'את 0, דריג'את","s":0,"t":0,"vo":false,"ci":359},{"o":13795843,"f":"סמיחה","l":"חאג' עאמר","v":"300833720","p":"","a":"דריג'את 0, דריג'את","s":0,"t":0,"vo":false,"ci":359},{"o":9277022,"f":"סמיר","l":"אבו חמאד","v":"040111304","p":"","a":"דריג'את 0, דריג'את","s":0,"t":0,"vo":false,"ci":359},{"o":12055140,"f":"פאטמה","l":"חאג' עאמר","v":"056964695","p":"","a":"דריג'את 0, דריג'את","s":0,"t":0,"vo":false,"ci":359},{"o":10996338,"f":"לטיפה","l":"אבו חמאד","v":"304717713","p":"","a":"דריג'את 0, דריג'את","s":0,"t":0,"vo":false,"ci":359},{"o":10674804,"f":"מופיד","l":"אבו חמאד","v":"203185871","p":"","a":"דריג'את 0, דריג'את","s":0,"t":0,"vo":false,"ci":359},{"o":8408664,"f":"ג'לאל","l":"אבו חמאד","v":"032486896","p":"","a":"דריג'את 0, דריג'את","s":0,"t":0,"vo":false,"ci":359},{"o":11246194,"f":"אדם","l":"אבו רביעה","v":"314801358","p":"","a":"דריג'את 0, דריג'את","s":0,"t":0,"vo":false,"ci":359},{"o":11299445,"f":"קוסאי","l":"אבו חמאד","v":"314803891","p":"","a":"דריג'את 0, דריג'את","s":0,"t":0,"vo":false,"ci":359},{"o":7485103,"f":"היאם","l":"אבו חמאד","v":"039205562","p":"","a":"דריג'את 0, דריג'את","s":0,"t":0,"vo":false,"ci":359},{"o":12274267,"f":"פאטמה","l":"אבו חמאד ח'ליפה","v":"058912759","p":"","a":"דריג'את 0, דריג'את","s":0,"t":0,"vo":false,"ci":359},{"o":12576351,"f":"סונה","l":"אבו חמאד","v":"026134247","p":"","a":"דריג'את 0, דריג'את","s":0,"t":0,"vo":false,"ci":359},{"o":13705776,"f":"מופת","l":"אבו רביעה","v":"319068086","p":"","a":"דריג'את 0, דריג'את","s":0,"t":0,"vo":false,"ci":359},{"o":11197006,"f":"חסן","l":"חאג' עאמר","v":"053060133","p":"","a":"דריג'את 0, דריג'את","s":0,"t":0,"vo":false,"ci":359},{"o":11598422,"f":"עזיזה","l":"אבו רביעה","v":"058561176","p":"","a":"דריג'את 0, דריג'את","s":0,"t":0,"vo":false,"ci":359},{"o":11615832,"f":"סאמהר","l":"אבו חמאד אלעוודה","v":"060681053","p":"","a":"דריג'את 0, דריג'את","s":0,"t":0,"vo":false,"ci":359},{"o":7429786,"f":"טריה","l":"אבו חמאד","v":"042835496","p":"","a":"דריג'את 0, דריג'את","s":0,"t":0,"vo":false,"ci":359},{"o":13534757,"f":"אנסאם","l":"אבו רביעה","v":"322328162","p":"","a":"דריג'את 0, דריג'את","s":0,"t":0,"vo":false,"ci":359},{"o":11672157,"f":"מחמד","l":"אבו חמאד","v":"301821112","p":"","a":"דריג'את 0, דריג'את","s":0,"t":0,"vo":false,"ci":359},{"o":9028216,"f":"רפעה","l":"אבו חמאד","v":"043167436","p":"","a":"דריג'את 0, דריג'את","s":0,"t":0,"vo":false,"ci":359},{"o":12110410,"f":"פיצל","l":"אבו חמאד","v":"033461716","p":"","a":"דריג'את 0, דריג'את","s":0,"t":0,"vo":false,"ci":359},{"o":11824711,"f":"עגאב","l":"אבו רביעה","v":"208970814","p":"","a":"דריג'את 0, דריג'את","s":0,"t":0,"vo":false,"ci":359},{"o":13267516,"f":"עובאידה","l":"רייט","v":"316003227","p":"","a":"דריג'את 0, דריג'את","s":0,"t":0,"vo":false,"ci":359},{"o":10094189,"f":"בושרה","l":"דריג'את","v":"209471887","p":"","a":"דריג'את 0, דריג'את","s":0,"t":0,"vo":false,"ci":359},{"o":9312886,"f":"שפה","l":"אבו חמאד","v":"029852753","p":"","a":"דריג'את 0, דריג'את","s":0,"t":0,"vo":false,"ci":359},{"o":12906041,"f":"כותר","l":"אבו חמאד אלעוודה","v":"203125240","p":"","a":"דריג'את 0, דריג'את","s":0,"t":0,"vo":false,"ci":359},{"o":9433712,"f":"פראס","l":"חאג' עאמר","v":"203724323","p":"","a":"דריג'את 0, דריג'את","s":0,"t":0,"vo":false,"ci":359},{"o":11242411,"f":"חמזה","l":"אבו חמאד","v":"314801036","p":"","a":"דריג'את 0, דריג'את","s":0,"t":0,"vo":false,"ci":359},{"o":13498317,"f":"נוף","l":"אבו חמאד","v":"057633547","p":"","a":"דריג'את 0, דריג'את","s":0,"t":0,"vo":false,"ci":359},{"o":13492172,"f":"ואליד","l":"אבו חמאד","v":"026427955","p":"","a":"דריג'את 0, דריג'את","s":0,"t":0,"vo":false,"ci":359},{"o":12230590,"f":"איסלח","l":"אבו רביעה","v":"201662640","p":"","a":"דריג'את 0, דריג'את","s":0,"t":0,"vo":false,"ci":359},{"o":13684692,"f":"אלהם","l":"אבו חמאד","v":"040884413","p":"","a":"דריג'את 0, דריג'את","s":0,"t":0,"vo":false,"ci":359},{"o":9087887,"f":"נאהדי","l":"אבו רביעה","v":"208228767","p":"","a":"דריג'את 0, דריג'את","s":0,"t":0,"vo":false,"ci":359},{"o":10503078,"f":"סנארית","l":"אלחואמדה","v":"206423931","p":"","a":"דריג'את 0, דריג'את","s":0,"t":0,"vo":false,"ci":359},{"o":8526730,"f":"גואהר","l":"אבו חמאד","v":"037769023","p":"","a":"דריג'את 0, דריג'את","s":0,"t":0,"vo":false,"ci":359},{"o":9355142,"f":"מחמד","l":"אבו חמאד","v":"300153426","p":"","a":"דריג'את 0, דריג'את","s":0,"t":0,"vo":false,"ci":359},{"o":11517862,"f":"יסמין","l":"אבו חמאד","v":"036295707","p":"","a":"דריג'את 0, דריג'את","s":0,"t":0,"vo":false,"ci":359},{"o":13610948,"f":"פאיזה","l":"אבו חמאד","v":"057570475","p":"","a":"דריג'את 0, דריג'את","s":0,"t":0,"vo":false,"ci":359},{"o":11674558,"f":"גאמל","l":"אבו חמאד","v":"302996160","p":"","a":"דריג'את 0, דריג'את","s":0,"t":0,"vo":false,"ci":359},{"o":11214758,"f":"עזאת","l":"אבו חמאד","v":"053838850","p":"","a":"דריג'את 0, דריג'את","s":0,"t":0,"vo":false,"ci":359},{"o":13390785,"f":"פאטמה","l":"דריגאת","v":"059519520","p":"","a":"דריג'את 0, דריג'את","s":0,"t":0,"vo":false,"ci":359},{"o":10189717,"f":"בהאגט","l":"אבו חמאד","v":"205556889","p":"","a":"דריג'את 0, דריג'את","s":0,"t":0,"vo":false,"ci":359},{"o":13040585,"f":"עאישה","l":"אלרמילי","v":"203063243","p":"","a":"דריג'את 0, דריג'את","s":0,"t":0,"vo":false,"ci":359},{"o":9527171,"f":"באסם","l":"אבו חמאד אלעוודה","v":"037287984","p":"","a":"דריג'את 0, דריג'את","s":0,"t":0,"vo":false,"ci":359},{"o":13668291,"f":"תאמר","l":"אבו רביעה","v":"318692753","p":"","a":"דריג'את 0, דריג'את","s":0,"t":0,"vo":false,"ci":359},{"o":13210590,"f":"סואעד","l":"אבו חמאד","v":"039779178","p":"","a":"דריג'את 0, דריג'את","s":0,"t":0,"vo":false,"ci":359},{"o":13800394,"f":"הנה","l":"אבו רביעה","v":"039350780","p":"","a":"דריג'את 0, דריג'את","s":0,"t":0,"vo":false,"ci":359},{"o":8368998,"f":"עוקב","l":"אבו רביעה","v":"066594987","p":"","a":"דריג'את 0, דריג'את","s":0,"t":0,"vo":false,"ci":359},{"o":13418454,"f":"יאסין","l":"אבו חמאד","v":"308174010","p":"","a":"דריג'את 0, דריג'את","s":0,"t":0,"vo":false,"ci":359},{"o":10412930,"f":"נאדא","l":"אבו חמאד","v":"205775265","p":"","a":"דריג'את 0, דריג'את","s":0,"t":0,"vo":false,"ci":359},{"o":10331008,"f":"מחמד","l":"אבו רביעה","v":"208399832","p":"","a":"דריג'את 0, דריג'את","s":0,"t":0,"vo":false,"ci":359},{"o":12426140,"f":"מאזן","l":"אבו חמאד","v":"034056523","p":"","a":"דריג'את 0, דריג'את","s":0,"t":0,"vo":false,"ci":359},{"o":13375470,"f":"סמי","l":"אבו רביעה","v":"311373468","p":"","a":"דריג'את 0, דריג'את","s":0,"t":0,"vo":false,"ci":359},{"o":8531873,"f":"פרוק","l":"אבו רביעה","v":"200250793","p":"","a":"דריג'את 0, דריג'את","s":0,"t":0,"vo":false,"ci":359},{"o":7788368,"f":"זוהיר","l":"אבו חמאד","v":"036464717","p":"","a":"דריג'את 0, דריג'את","s":0,"t":0,"vo":false,"ci":359},{"o":13498346,"f":"עטא","l":"רייט","v":"057633539","p":"","a":"דריג'את 0, דריג'את","s":0,"t":0,"vo":false,"ci":359},{"o":13019119,"f":"ראמי","l":"אבו רביעה","v":"323984310","p":"","a":"דריג'את 0, דריג'את","s":0,"t":0,"vo":false,"ci":359},{"o":10130353,"f":"עישה","l":"אבו רביעה","v":"025880287","p":"","a":"דריג'את 0, דריג'את","s":0,"t":0,"vo":false,"ci":359},{"o":8049480,"f":"מואייד","l":"אבו חמאד","v":"200305316","p":"","a":"דריג'את 0, דריג'את","s":0,"t":0,"vo":false,"ci":359},{"o":7469890,"f":"מחמד","l":"אבו חמאד","v":"203296785","p":"","a":"דריג'את 0, דריג'את","s":0,"t":0,"vo":false,"ci":359},{"o":7496521,"f":"באשא","l":"חורפש","v":"301363693","p":"","a":"דריג'את 0, דריג'את","s":0,"t":0,"vo":false,"ci":359},{"o":12251015,"f":"סלימה","l":"אבו רביעה","v":"315400838","p":"","a":"דריג'את 0, דריג'את","s":0,"t":0,"vo":false,"ci":359},{"o":13974504,"f":"חנאן","l":"אבן חמאד","v":"031518277","p":"","a":"דריג'את 0, דריג'את","s":0,"t":0,"vo":false,"ci":359},{"o":10019802,"f":"מהר","l":"אבו חמאד","v":"209470053","p":"","a":"דריג'את 0, דריג'את","s":0,"t":0,"vo":false,"ci":359},{"o":11822070,"f":"נור","l":"אבו חמאד","v":"316077718","p":"","a":"דריג'את 0, דריג'את","s":0,"t":0,"vo":false,"ci":359},{"o":12988292,"f":"כפאיה","l":"אבו חמאד","v":"316589779","p":"","a":"דריג'את 0, דריג'את","s":0,"t":0,"vo":false,"ci":359},{"o":13805462,"f":"עבאס","l":"אלרייאט","v":"301575130","p":"","a":"דריג'את 0, דריג'את","s":0,"t":0,"vo":false,"ci":359},{"o":7469878,"f":"אמאני","l":"אבו חמאד","v":"203296777","p":"","a":"דריג'את 0, דריג'את","s":0,"t":0,"vo":false,"ci":359},{"o":10300378,"f":"נוסאף","l":"אבו-חמאד אלעוודה","v":"031556491","p":"","a":"דריג'את 0, דריג'את","s":0,"t":0,"vo":false,"ci":359},{"o":10630117,"f":"מחמד","l":"אבו חמאד","v":"208894741","p":"","a":"דריג'את 0, דריג'את","s":0,"t":0,"vo":false,"ci":359},{"o":13893531,"f":"אמירה","l":"קרעאן","v":"026214841","p":"","a":"דריג'את 0, דריג'את","s":0,"t":0,"vo":false,"ci":359},{"o":10922991,"f":"אברהים","l":"אבו חמאד","v":"027620525","p":"","a":"דריג'את 0, דריג'את","s":0,"t":0,"vo":false,"ci":359},{"o":8688596,"f":"אשרף","l":"אבו חמאד","v":"203003512","p":"","a":"דריג'את 0, דריג'את","s":0,"t":0,"vo":false,"ci":359},{"o":13071255,"f":"אימאן","l":"אבו חמאד","v":"066418427","p":"","a":"דריג'את 0, דריג'את","s":0,"t":0,"vo":false,"ci":359},{"o":11048954,"f":"עבד אללה","l":"אבו רביעה","v":"316340413","p":"","a":"דריג'את 0, דריג'את","s":0,"t":0,"vo":false,"ci":359},{"o":9835459,"f":"סארי","l":"אבו רביעה","v":"203512108","p":"","a":"דריג'את 0, דריג'את","s":0,"t":0,"vo":false,"ci":359},{"o":7549732,"f":"נמר","l":"אבו רביעה","v":"054467535","p":"","a":"דריג'את 0, דריג'את","s":0,"t":0,"vo":false,"ci":359},{"o":9358294,"f":"אחמד","l":"אבו רביעה","v":"029855954","p":"","a":"דריג'את 0, דריג'את","s":0,"t":0,"vo":false,"ci":359},{"o":9831372,"f":"עאדל","l":"אבו רביעה","v":"056932817","p":"","a":"דריג'את 0, דריג'את","s":0,"t":0,"vo":false,"ci":359},{"o":10474436,"f":"עליאן","l":"אבו חמאד","v":"023295496","p":"","a":"דריג'את 0, דריג'את","s":0,"t":0,"vo":false,"ci":359},{"o":13755274,"f":"אדם","l":"אבו רביעה","v":"203415583","p":"","a":"דריג'את 0, דריג'את","s":0,"t":0,"vo":false,"ci":359},{"o":13907893,"f":"סוהל","l":"דריג'את","v":"318543832","p":"","a":"דריג'את 0, דריג'את","s":0,"t":0,"vo":false,"ci":359},{"o":7549712,"f":"עזיה","l":"אבו רביעה","v":"054467527","p":"","a":"דריג'את 0, דריג'את","s":0,"t":0,"vo":false,"ci":359},{"o":12661670,"f":"לפי","l":"אבו חמאד","v":"026135954","p":"","a":"דריג'את 0, דריג'את","s":0,"t":0,"vo":false,"ci":359},{"o":12929964,"f":"מייאדה","l":"אבו חמאד","v":"206738494","p":"","a":"דריג'את 0, דריג'את","s":0,"t":0,"vo":false,"ci":359},{"o":10165233,"f":"עזאם","l":"אבו חמאד","v":"066036807","p":"","a":"דריג'את 0, דריג'את","s":0,"t":0,"vo":false,"ci":359},{"o":13791160,"f":"רוקיה","l":"אבו חמאד","v":"300833076","p":"","a":"דריג'את 0, דריג'את","s":0,"t":0,"vo":false,"ci":359},{"o":10932170,"f":"סופיאן","l":"אבו רביעה","v":"205569122","p":"","a":"דריג'את 0, דריג'את","s":0,"t":0,"vo":false,"ci":359},{"o":7644953,"f":"שהירה","l":"חאג' עאמר","v":"017711797","p":"","a":"דריג'את 0, דריג'את","s":0,"t":0,"vo":false,"ci":359},{"o":13757375,"f":"עומאר","l":"אבו-חמאד אלעוודה","v":"211619309","p":"","a":"דריג'את 0, דריג'את","s":0,"t":0,"vo":false,"ci":359},{"o":9622525,"f":"רודינה","l":"חאג' עאמר","v":"309635142","p":"","a":"דריג'את 0, דריג'את","s":0,"t":0,"vo":false,"ci":359},{"o":12732333,"f":"סוהיב","l":"חאג' עאמר","v":"314823139","p":"","a":"דריג'את 0, דריג'את","s":0,"t":0,"vo":false,"ci":359},{"o":12909483,"f":"תמים","l":"אבו רביעה","v":"203125612","p":"","a":"דריג'את 0, דריג'את","s":0,"t":0,"vo":false,"ci":359},{"o":9434111,"f":"סארה","l":"אבו חמאד","v":"035188648","p":"","a":"דריג'את 0, דריג'את","s":0,"t":0,"vo":false,"ci":359},{"o":10959835,"f":"רימאן","l":"אלרייאט","v":"205568090","p":"","a":"דריג'את 0, דריג'את","s":0,"t":0,"vo":false,"ci":359},{"o":10290144,"f":"מרים","l":"אלרייאט","v":"023353444","p":"","a":"דריג'את 0, דריג'את","s":0,"t":0,"vo":false,"ci":359},{"o":13824943,"f":"קאמל","l":"אבו רביעה","v":"203417415","p":"","a":"דריג'את 0, דריג'את","s":0,"t":0,"vo":false,"ci":359},{"o":13884333,"f":"איאת","l":"חאג' עאמר","v":"322482506","p":"","a":"דריג'את 0, דריג'את","s":0,"t":0,"vo":false,"ci":359},{"o":7586572,"f":"נסים","l":"אבו רביעה","v":"315588970","p":"","a":"דריג'את 0, דריג'את","s":0,"t":0,"vo":false,"ci":359},{"o":10922969,"f":"עדנאן","l":"אבו חמאד","v":"027620517","p":"","a":"דריג'את 0, דריג'את","s":0,"t":0,"vo":false,"ci":359},{"o":12036040,"f":"עאיד","l":"אבו רביעה","v":"029953122","p":"","a":"דריג'את 0, דריג'את","s":0,"t":0,"vo":false,"ci":359},{"o":13094727,"f":"נורה","l":"אבו רביעה","v":"316433267","p":"","a":"דריג'את 0, דריג'את","s":0,"t":0,"vo":false,"ci":359},{"o":8204280,"f":"חולוד","l":"אבו חמאד","v":"318276748","p":"","a":"דריג'את 0, דריג'את","s":0,"t":0,"vo":false,"ci":359},{"o":13022017,"f":"עטיה","l":"אבן חמאד","v":"211607973","p":"","a":"דריג'את 0, דריג'את","s":0,"t":0,"vo":false,"ci":359},{"o":13340483,"f":"הודה","l":"אבו חמאד","v":"026421305","p":"","a":"דריג'את 0, דריג'את","s":0,"t":0,"vo":false,"ci":359},{"o":13282115,"f":"ראדיה","l":"אבו חמאד","v":"059515205","p":"","a":"דריג'את 0, דריג'את","s":0,"t":0,"vo":false,"ci":359},{"o":9245441,"f":"תיסיר","l":"אבו רביעה","v":"026302158","p":"","a":"דריג'את 0, דריג'את","s":0,"t":0,"vo":false,"ci":359},{"o":8061942,"f":"שרה","l":"אבו רביעה","v":"200304186","p":"","a":"דריג'את 0, דריג'את","s":0,"t":0,"vo":false,"ci":359},{"o":13783903,"f":"גאדה","l":"אבו חמאד","v":"304752801","p":"","a":"דריג'את 0, דריג'את","s":0,"t":0,"vo":false,"ci":359},{"o":10566449,"f":"רולה","l":"אבן חמאד","v":"205621923","p":"","a":"דריג'את 0, דריג'את","s":0,"t":0,"vo":false,"ci":359},{"o":8383469,"f":"הלאל","l":"אבו חמאד","v":"066595695","p":"","a":"דריג'את 0, דריג'את","s":0,"t":0,"vo":false,"ci":359},{"o":11467580,"f":"ודאד","l":"אבו חמאד","v":"203196969","p":"","a":"דריג'את 0, דריג'את","s":0,"t":0,"vo":false,"ci":359},{"o":10670900,"f":"זינב","l":"אבו חמאד","v":"201089596","p":"","a":"דריג'את 0, דריג'את","s":0,"t":0,"vo":false,"ci":359},{"o":11977504,"f":"תהר","l":"אבן חמאד","v":"315619320","p":"","a":"דריג'את 0, דריג'את","s":0,"t":0,"vo":false,"ci":359},{"o":13035344,"f":"מרווא","l":"אבו חאמד","v":"316431147","p":"","a":"דריג'את 0, דריג'את","s":0,"t":0,"vo":false,"ci":359},{"o":13068113,"f":"בולאל","l":"אבו רביעה","v":"203064316","p":"","a":"דריג'את 0, דריג'את","s":0,"t":0,"vo":false,"ci":359},{"o":12268332,"f":"נגאח","l":"אבו חמאד","v":"029895372","p":"","a":"דריג'את 0, דריג'את","s":0,"t":0,"vo":false,"ci":359},{"o":12286764,"f":"מוניר","l":"ארייט","v":"026349837","p":"","a":"דריג'את 0, דריג'את","s":0,"t":0,"vo":false,"ci":359},{"o":10233605,"f":"בדר","l":"אבו רביעה","v":"023351109","p":"","a":"דריג'את 0, דריג'את","s":0,"t":0,"vo":false,"ci":359},{"o":12081950,"f":"סועד","l":"חאג' חסן","v":"046230546","p":"","a":"דריג'את 0, דריג'את","s":0,"t":0,"vo":false,"ci":359},{"o":8848160,"f":"לוטפיאה","l":"אבו חמאד","v":"023333966","p":"","a":"דריג'את 0, דריג'את","s":0,"t":0,"vo":false,"ci":359},{"o":12438298,"f":"סמי","l":"אבן חמאד","v":"028384659","p":"","a":"דריג'את 0, דריג'את","s":0,"t":0,"vo":false,"ci":359},{"o":13048672,"f":"לינה","l":"אבו רביעה","v":"207325267","p":"","a":"דריג'את 0, דריג'את","s":0,"t":0,"vo":false,"ci":359},{"o":12393236,"f":"ח'אלד","l":"אבו חמאד","v":"028382703","p":"","a":"דריג'את 0, דריג'את","s":0,"t":0,"vo":false,"ci":359},{"o":10777358,"f":"באג'ס","l":"אבו-חמאד אלעוודה","v":"029163581","p":"","a":"דריג'את 0, דריג'את","s":0,"t":0,"vo":false,"ci":359},{"o":10426164,"f":"סעדיה","l":"אבו רביעה","v":"024717746","p":"","a":"דריג'את 0, דריג'את","s":0,"t":0,"vo":false,"ci":359},{"o":11457285,"f":"עבדל כרים","l":"אבו חמאד","v":"046225975","p":"","a":"דריג'את 0, דריג'את","s":0,"t":0,"vo":false,"ci":359},{"o":7917513,"f":"סאלם","l":"אבו חמאד","v":"324011766","p":"","a":"דריג'את 0, דריג'את","s":0,"t":0,"vo":false,"ci":359},{"o":9298748,"f":"דאווד","l":"אבו חמאד","v":"023400666","p":"","a":"דריג'את 0, דריג'את","s":0,"t":0,"vo":false,"ci":359},{"o":9778983,"f":"אלא","l":"אבו רביעה","v":"318859709","p":"","a":"דריג'את 0, דריג'את","s":0,"t":0,"vo":false,"ci":359},{"o":11703041,"f":"וגיה","l":"אבו חמאד","v":"301820783","p":"","a":"דריג'את 0, דריג'את","s":0,"t":0,"vo":false,"ci":359},{"o":12610419,"f":"ראיד","l":"אבו חמאד","v":"061992103","p":"","a":"דריג'את 0, דריג'את","s":0,"t":0,"vo":false,"ci":359},{"o":11078428,"f":"ודחה","l":"אבו חמאד","v":"052474152","p":"","a":"דריג'את 0, דריג'את","s":0,"t":0,"vo":false,"ci":359},{"o":11794181,"f":"אינתסאר","l":"אבו רביע","v":"033241159","p":"","a":"דריג'את 0, דריג'את","s":0,"t":0,"vo":false,"ci":359},{"o":10102562,"f":"זאהר","l":"אבו חמאד","v":"315742635","p":"","a":"דריג'את 0, דריג'את","s":0,"t":0,"vo":false,"ci":359},{"o":10784540,"f":"אתיר","l":"אבו רביעה","v":"208031500","p":"","a":"דריג'את 0, דריג'את","s":0,"t":0,"vo":false,"ci":359},{"o":9266996,"f":"רוואן","l":"אבו חמאד","v":"324025949","p":"","a":"דריג'את 0, דריג'את","s":0,"t":0,"vo":false,"ci":359},{"o":7978937,"f":"לינדה","l":"אבו חאמד","v":"206818486","p":"","a":"דריג'את 0, דריג'את","s":0,"t":0,"vo":false,"ci":359},{"o":12468090,"f":"מאמון","l":"אבו רביעה","v":"037236684","p":"","a":"דריג'את 0, דריג'את","s":0,"t":0,"vo":false,"ci":359},{"o":10539882,"f":"רבאח","l":"אבו חמאד","v":"207166877","p":"","a":"דריג'את 0, דריג'את","s":0,"t":0,"vo":false,"ci":359},{"o":8517450,"f":"אימאן","l":"אבו רביעה","v":"212650329","p":"","a":"דריג'את 0, דריג'את","s":0,"t":0,"vo":false,"ci":359},{"o":8727368,"f":"נוח","l":"אבו רביעה","v":"322411034","p":"","a":"דריג'את 0, דריג'את","s":0,"t":0,"vo":false,"ci":359},{"o":10721134,"f":"פאתן","l":"אבו רביעה","v":"208899658","p":"","a":"דריג'את 0, דריג'את","s":0,"t":0,"vo":false,"ci":359},{"o":9433951,"f":"נאגי","l":"אבו חמאד","v":"035188598","p":"","a":"דריג'את 0, דריג'את","s":0,"t":0,"vo":false,"ci":359},{"o":8126378,"f":"מרים","l":"אבו חמאד","v":"040894362","p":"","a":"דריג'את 0, דריג'את","s":0,"t":0,"vo":false,"ci":359},{"o":13737728,"f":"סיהא","l":"אבו חמאד","v":"308301688","p":"","a":"דריג'את 0, דריג'את","s":0,"t":0,"vo":false,"ci":359},{"o":13735682,"f":"מוחמד","l":"אבו חמאד","v":"035218288","p":"","a":"דריג'את 0, דריג'את","s":0,"t":0,"vo":false,"ci":359},{"o":13756164,"f":"שירין","l":"אבו רביעה","v":"211619176","p":"","a":"דריג'את 0, דריג'את","s":0,"t":0,"vo":false,"ci":359},{"o":8722259,"f":"יסמין","l":"חאג' עאמר","v":"301872487","p":"","a":"דריג'את 0, דריג'את","s":0,"t":0,"vo":false,"ci":359},{"o":12700439,"f":"נבילה","l":"אבו חמאד","v":"313189292","p":"","a":"דריג'את 0, דריג'את","s":0,"t":0,"vo":false,"ci":359},{"o":13495067,"f":"סמיחה","l":"אבו חמאד","v":"057633265","p":"","a":"דריג'את 0, דריג'את","s":0,"t":0,"vo":false,"ci":359},{"o":13800196,"f":"עאישה","l":"אבו רביעה","v":"040889016","p":"","a":"דריג'את 0, דריג'את","s":0,"t":0,"vo":false,"ci":359},{"o":11385718,"f":"מאגד","l":"דריגאת","v":"023150311","p":"","a":"דריג'את 0, דריג'את","s":0,"t":0,"vo":false,"ci":359},{"o":11145077,"f":"יוסאם","l":"אבו חמאד","v":"026482489","p":"","a":"דריג'את 0, דריג'את","s":0,"t":0,"vo":false,"ci":359},{"o":12501854,"f":"דיאב","l":"אבו חמאד","v":"318182896","p":"","a":"דריג'את 0, דריג'את","s":0,"t":0,"vo":false,"ci":359},{"o":10017658,"f":"פאטמה","l":"אבו חמאד","v":"053694808","p":"","a":"דריג'את 0, דריג'את","s":0,"t":0,"vo":false,"ci":359},{"o":12694307,"f":"רסמיה","l":"אבו רביעה","v":"059441071","p":"","a":"דריג'את 0, דריג'את","s":0,"t":0,"vo":false,"ci":359},{"o":7664542,"f":"שאקר","l":"אלרייאט","v":"055764401","p":"","a":"דריג'את 0, דריג'את","s":0,"t":0,"vo":false,"ci":359},{"o":11624282,"f":"ליאלי","l":"אבו מטיר","v":"312216989","p":"","a":"דריג'את 0, דריג'את","s":0,"t":0,"vo":false,"ci":359},{"o":12858159,"f":"נאדי","l":"אבו רביעה","v":"318747763","p":"","a":"דריג'את 0, דריג'את","s":0,"t":0,"vo":false,"ci":359},{"o":8057748,"f":"שימה","l":"אבו חמאד","v":"322616137","p":"","a":"דריג'את 0, דריג'את","s":0,"t":0,"vo":false,"ci":359},{"o":7926679,"f":"זהאר","l":"אבן חמאד","v":"318822632","p":"","a":"דריג'את 0, דריג'את","s":0,"t":0,"vo":false,"ci":359},{"o":13396771,"f":"וסים","l":"אבו חמאד","v":"208904573","p":"","a":"דריג'את 0, דריג'את","s":0,"t":0,"vo":false,"ci":359},{"o":9244541,"f":"עיידה","l":"אבו רביעה","v":"026302026","p":"","a":"דריג'את 0, דריג'את","s":0,"t":0,"vo":false,"ci":359},{"o":7414658,"f":"אומימה","l":"אבו חמאד","v":"203290176","p":"","a":"דריג'את 0, דריג'את","s":0,"t":0,"vo":false,"ci":359},{"o":7598976,"f":"מוהנד","l":"אבו חמאד","v":"207775776","p":"","a":"דריג'את 0, דריג'את","s":0,"t":0,"vo":false,"ci":359},{"o":10678100,"f":"חיטם","l":"אבו חמאד","v":"205626237","p":"","a":"דריג'את 0, דריג'את","s":0,"t":0,"vo":false,"ci":359},{"o":12740410,"f":"וסאל","l":"אבו חמאד","v":"201456530","p":"","a":"דריג'את 0, דריג'את","s":0,"t":0,"vo":false,"ci":359},{"o":11806541,"f":"אנעאם","l":"אבו חמאד","v":"315612663","p":"","a":"דריג'את 0, דריג'את","s":0,"t":0,"vo":false,"ci":359},{"o":10908508,"f":"אדם","l":"אבו רביעה","v":"312207038","p":"","a":"דריג'את 0, דריג'את","s":0,"t":0,"vo":false,"ci":359},{"o":11998029,"f":"רפעה","l":"אבו קרינאת","v":"029950946","p":"","a":"דריג'את 0, דריג'את","s":0,"t":0,"vo":false,"ci":359},{"o":8359811,"f":"האיל","l":"אבו חמאד","v":"201486271","p":"","a":"דריג'את 0, דריג'את","s":0,"t":0,"vo":false,"ci":359}],"citiesOids":[359],"hasMore":false}